{
"meta":{"test_sets":[],"test_metrics":[],"learn_metrics":[{"best_value":"Min","name":"RMSE"}],"launch_mode":"Train","parameters":"","iteration_count":1000,"learn_sets":["learn"],"name":"experiment"},
"iterations":[
{"learn":[5690709.862],"iteration":0,"passed_time":0.003033688648,"remaining_time":3.03065496},
{"learn":[5417455.797],"iteration":1,"passed_time":0.005665802016,"remaining_time":2.827235206},
{"learn":[5151143.887],"iteration":2,"passed_time":0.007661221465,"remaining_time":2.546079267},
{"learn":[4916215.923],"iteration":3,"passed_time":0.009714707921,"remaining_time":2.418962272},
{"learn":[4703292.134],"iteration":4,"passed_time":0.01208075518,"remaining_time":2.40407028},
{"learn":[4494211.819],"iteration":5,"passed_time":0.01458029589,"remaining_time":2.41546902},
{"learn":[4300575.017],"iteration":6,"passed_time":0.01706339055,"remaining_time":2.420563831},
{"learn":[4122924.301],"iteration":7,"passed_time":0.01921798994,"remaining_time":2.383030752},
{"learn":[3958380.899],"iteration":8,"passed_time":0.02117878254,"remaining_time":2.332019278},
{"learn":[3809511.053],"iteration":9,"passed_time":0.02336584514,"remaining_time":2.313218669},
{"learn":[3667154.898],"iteration":10,"passed_time":0.02539025255,"remaining_time":2.282814525},
{"learn":[3539191.313],"iteration":11,"passed_time":0.02716087834,"remaining_time":2.23624565},
{"learn":[3420334.596],"iteration":12,"passed_time":0.02911964813,"remaining_time":2.210853285},
{"learn":[3308998.253],"iteration":13,"passed_time":0.03139320437,"remaining_time":2.210978536},
{"learn":[3210665.965],"iteration":14,"passed_time":0.03453064274,"remaining_time":2.267512207},
{"learn":[3123923.345],"iteration":15,"passed_time":0.0374021794,"remaining_time":2.300234033},
{"learn":[3038172.345],"iteration":16,"passed_time":0.03979806826,"remaining_time":2.30126477},
{"learn":[2957419.599],"iteration":17,"passed_time":0.04181651607,"remaining_time":2.281323266},
{"learn":[2886852.835],"iteration":18,"passed_time":0.04373158687,"remaining_time":2.25793088},
{"learn":[2820878.613],"iteration":19,"passed_time":0.04583986404,"remaining_time":2.246153338},
{"learn":[2757834.438],"iteration":20,"passed_time":0.04790756737,"remaining_time":2.233405164},
{"learn":[2702232.275],"iteration":21,"passed_time":0.0498233119,"remaining_time":2.214872684},
{"learn":[2650328.495],"iteration":22,"passed_time":0.05210379215,"remaining_time":2.213278475},
{"learn":[2599496.378],"iteration":23,"passed_time":0.0546184896,"remaining_time":2.22115191},
{"learn":[2554885.596],"iteration":24,"passed_time":0.05747420807,"remaining_time":2.241494115},
{"learn":[2511737.754],"iteration":25,"passed_time":0.059444306,"remaining_time":2.226875156},
{"learn":[2472918.468],"iteration":26,"passed_time":0.06172938288,"remaining_time":2.224544057},
{"learn":[2438200.187],"iteration":27,"passed_time":0.06380908647,"remaining_time":2.215086859},
{"learn":[2404674.357],"iteration":28,"passed_time":0.06618650741,"remaining_time":2.216106852},
{"learn":[2372977.865],"iteration":29,"passed_time":0.06861984982,"remaining_time":2.218708477},
{"learn":[2342862.936],"iteration":30,"passed_time":0.07426385208,"remaining_time":2.321344279},
{"learn":[2316146.176],"iteration":31,"passed_time":0.07702851096,"remaining_time":2.330112457},
{"learn":[2292119.604],"iteration":32,"passed_time":0.07949730704,"remaining_time":2.329511997},
{"learn":[2270383.233],"iteration":33,"passed_time":0.08172451909,"remaining_time":2.321937807},
{"learn":[2249329.853],"iteration":34,"passed_time":0.08363034722,"remaining_time":2.305808145},
{"learn":[2228940.786],"iteration":35,"passed_time":0.08571717733,"remaining_time":2.295315526},
{"learn":[2212249.237],"iteration":36,"passed_time":0.08752653146,"remaining_time":2.2780554},
{"learn":[2194955.565],"iteration":37,"passed_time":0.08951261425,"remaining_time":2.266082498},
{"learn":[2180712.274],"iteration":38,"passed_time":0.0921134956,"remaining_time":2.269771007},
{"learn":[2164070.841],"iteration":39,"passed_time":0.09488607844,"remaining_time":2.277265883},
{"learn":[2150640.065],"iteration":40,"passed_time":0.09757977702,"remaining_time":2.282414784},
{"learn":[2137962.315],"iteration":41,"passed_time":0.1000384949,"remaining_time":2.281830431},
{"learn":[2123813.034],"iteration":42,"passed_time":0.1025548786,"remaining_time":2.282442298},
{"learn":[2110757.387],"iteration":43,"passed_time":0.1046619672,"remaining_time":2.274019106},
{"learn":[2099336.075],"iteration":44,"passed_time":0.1067344135,"remaining_time":2.265141441},
{"learn":[2088941.689],"iteration":45,"passed_time":0.1088139575,"remaining_time":2.256706858},
{"learn":[2079525.678],"iteration":46,"passed_time":0.1114797294,"remaining_time":2.260429407},
{"learn":[2070070.666],"iteration":47,"passed_time":0.1142926009,"remaining_time":2.266803252},
{"learn":[2061568.439],"iteration":48,"passed_time":0.1164071006,"remaining_time":2.259248014},
{"learn":[2054625.859],"iteration":49,"passed_time":0.1183977144,"remaining_time":2.249556575},
{"learn":[2046664.018],"iteration":50,"passed_time":0.1203423497,"remaining_time":2.239311567},
{"learn":[2037791.803],"iteration":51,"passed_time":0.1223312663,"remaining_time":2.230193086},
{"learn":[2030117.671],"iteration":52,"passed_time":0.1246498991,"remaining_time":2.227234989},
{"learn":[2024032.377],"iteration":53,"passed_time":0.1273842939,"remaining_time":2.231584112},
{"learn":[2014549.792],"iteration":54,"passed_time":0.131874078,"remaining_time":2.265836431},
{"learn":[2008573.695],"iteration":55,"passed_time":0.1357075531,"remaining_time":2.287641609},
{"learn":[2000986.063],"iteration":56,"passed_time":0.1384617756,"remaining_time":2.290692182},
{"learn":[1996524.623],"iteration":57,"passed_time":0.142144432,"remaining_time":2.308621636},
{"learn":[1989609.8],"iteration":58,"passed_time":0.1465168211,"remaining_time":2.33681913},
{"learn":[1985088.757],"iteration":59,"passed_time":0.1492030434,"remaining_time":2.337514347},
{"learn":[1976831.413],"iteration":60,"passed_time":0.1516724376,"remaining_time":2.334760966},
{"learn":[1972979.552],"iteration":61,"passed_time":0.1539459448,"remaining_time":2.329053165},
{"learn":[1967982.46],"iteration":62,"passed_time":0.1559766277,"remaining_time":2.319842859},
{"learn":[1962581.164],"iteration":63,"passed_time":0.15885747,"remaining_time":2.323290499},
{"learn":[1956477.125],"iteration":64,"passed_time":0.1617564107,"remaining_time":2.326803754},
{"learn":[1948329.877],"iteration":65,"passed_time":0.1644159779,"remaining_time":2.326735203},
{"learn":[1943033.429],"iteration":66,"passed_time":0.1668631819,"remaining_time":2.32363207},
{"learn":[1939196.298],"iteration":67,"passed_time":0.1706511461,"remaining_time":2.338924531},
{"learn":[1936350.62],"iteration":68,"passed_time":0.1729573063,"remaining_time":2.333670322},
{"learn":[1929243.19],"iteration":69,"passed_time":0.1750797542,"remaining_time":2.326059591},
{"learn":[1926053.609],"iteration":70,"passed_time":0.1776546232,"remaining_time":2.324523168},
{"learn":[1921085.541],"iteration":71,"passed_time":0.1797366651,"remaining_time":2.316605906},
{"learn":[1917403.884],"iteration":72,"passed_time":0.1818278348,"remaining_time":2.308964422},
{"learn":[1914570.927],"iteration":73,"passed_time":0.1842335412,"remaining_time":2.305408907},
{"learn":[1909515.053],"iteration":74,"passed_time":0.1865406704,"remaining_time":2.300668268},
{"learn":[1905098.284],"iteration":75,"passed_time":0.1889425935,"remaining_time":2.297144163},
{"learn":[1899935.547],"iteration":76,"passed_time":0.1921161092,"remaining_time":2.302898296},
{"learn":[1897414.117],"iteration":77,"passed_time":0.1942584519,"remaining_time":2.296234521},
{"learn":[1893342.761],"iteration":78,"passed_time":0.1971410576,"remaining_time":2.298315368},
{"learn":[1890032.65],"iteration":79,"passed_time":0.20016857,"remaining_time":2.301938555},
{"learn":[1885542.986],"iteration":80,"passed_time":0.2026468254,"remaining_time":2.299165834},
{"learn":[1879588.205],"iteration":81,"passed_time":0.2045698806,"remaining_time":2.290184761},
{"learn":[1876246.12],"iteration":82,"passed_time":0.2073531327,"remaining_time":2.290877382},
{"learn":[1872114.253],"iteration":83,"passed_time":0.2107065668,"remaining_time":2.297704943},
{"learn":[1866542.117],"iteration":84,"passed_time":0.2131389448,"remaining_time":2.294378053},
{"learn":[1864623.147],"iteration":85,"passed_time":0.2154788838,"remaining_time":2.290089532},
{"learn":[1860337.216],"iteration":86,"passed_time":0.2176274719,"remaining_time":2.283837722},
{"learn":[1855365.923],"iteration":87,"passed_time":0.2200887832,"remaining_time":2.280920117},
{"learn":[1850821.003],"iteration":88,"passed_time":0.2222064846,"remaining_time":2.27449559},
{"learn":[1846731.95],"iteration":89,"passed_time":0.2244638034,"remaining_time":2.269578457},
{"learn":[1842444.563],"iteration":90,"passed_time":0.2276301952,"remaining_time":2.273800521},
{"learn":[1840178.261],"iteration":91,"passed_time":0.2314604957,"remaining_time":2.284414458},
{"learn":[1836124.033],"iteration":92,"passed_time":0.2335710444,"remaining_time":2.277945562},
{"learn":[1834945.572],"iteration":93,"passed_time":0.235861641,"remaining_time":2.273304752},
{"learn":[1832100.547],"iteration":94,"passed_time":0.2378776248,"remaining_time":2.266097373},
{"learn":[1828778.337],"iteration":95,"passed_time":0.2400474578,"remaining_time":2.260446894},
{"learn":[1827394.092],"iteration":96,"passed_time":0.2421501345,"remaining_time":2.254243005},
{"learn":[1822882.193],"iteration":97,"passed_time":0.2444827593,"remaining_time":2.250239274},
{"learn":[1821426.587],"iteration":98,"passed_time":0.2473010029,"remaining_time":2.250688925},
{"learn":[1817654.18],"iteration":99,"passed_time":0.2499914239,"remaining_time":2.249922815},
{"learn":[1815277.166],"iteration":100,"passed_time":0.2522289767,"remaining_time":2.245087625},
{"learn":[1812537.109],"iteration":101,"passed_time":0.2545068386,"remaining_time":2.240658246},
{"learn":[1808609.096],"iteration":102,"passed_time":0.2566653673,"remaining_time":2.235231403},
{"learn":[1805570.526],"iteration":103,"passed_time":0.2589330832,"remaining_time":2.230808101},
{"learn":[1802718.833],"iteration":104,"passed_time":0.261679008,"remaining_time":2.230502021},
{"learn":[1799505.937],"iteration":105,"passed_time":0.2646418872,"remaining_time":2.23197969},
{"learn":[1797102.627],"iteration":106,"passed_time":0.2672466863,"remaining_time":2.230385896},
{"learn":[1795033.884],"iteration":107,"passed_time":0.2696434546,"remaining_time":2.227055199},
{"learn":[1792505.128],"iteration":108,"passed_time":0.2715903707,"remaining_time":2.220064407},
{"learn":[1790291.576],"iteration":109,"passed_time":0.2761382464,"remaining_time":2.234209448},
{"learn":[1786489.271],"iteration":110,"passed_time":0.2784456046,"remaining_time":2.230073356},
{"learn":[1781462.292],"iteration":111,"passed_time":0.2808221467,"remaining_time":2.226518449},
{"learn":[1779698.678],"iteration":112,"passed_time":0.2832172633,"remaining_time":2.2231302},
{"learn":[1776596.451],"iteration":113,"passed_time":0.2859878682,"remaining_time":2.222677643},
{"learn":[1773754.131],"iteration":114,"passed_time":0.288593811,"remaining_time":2.220917589},
{"learn":[1772132.775],"iteration":115,"passed_time":0.291108793,"remaining_time":2.218449767},
{"learn":[1769613.093],"iteration":116,"passed_time":0.2938661177,"remaining_time":2.217810102},
{"learn":[1767566.833],"iteration":117,"passed_time":0.2966479206,"remaining_time":2.217317508},
{"learn":[1765109.645],"iteration":118,"passed_time":0.2986398748,"remaining_time":2.210938905},
{"learn":[1763243.317],"iteration":119,"passed_time":0.3006867018,"remaining_time":2.205035813},
{"learn":[1760869.514],"iteration":120,"passed_time":0.3035122838,"remaining_time":2.204853698},
{"learn":[1759665.233],"iteration":121,"passed_time":0.3066499837,"remaining_time":2.206874473},
{"learn":[1757481.591],"iteration":122,"passed_time":0.3088685832,"remaining_time":2.20225811},
{"learn":[1755664.943],"iteration":123,"passed_time":0.3110391675,"remaining_time":2.197341215},
{"learn":[1753063.405],"iteration":124,"passed_time":0.3133281602,"remaining_time":2.193297121},
{"learn":[1750493.547],"iteration":125,"passed_time":0.3154044134,"remaining_time":2.187805217},
{"learn":[1747745.461],"iteration":126,"passed_time":0.3175501415,"remaining_time":2.182844673},
{"learn":[1746668.596],"iteration":127,"passed_time":0.3193982986,"remaining_time":2.175900909},
{"learn":[1745339.834],"iteration":128,"passed_time":0.3224162663,"remaining_time":2.176934635},
{"learn":[1744082.871],"iteration":129,"passed_time":0.326185167,"remaining_time":2.182931502},
{"learn":[1741478.31],"iteration":130,"passed_time":0.328735632,"remaining_time":2.180696673},
{"learn":[1738880.719],"iteration":131,"passed_time":0.3328380393,"remaining_time":2.188662258},
{"learn":[1736317.324],"iteration":132,"passed_time":0.3352457275,"remaining_time":2.18539884},
{"learn":[1734019.446],"iteration":133,"passed_time":0.3376945603,"remaining_time":2.182414099},
{"learn":[1731339.455],"iteration":134,"passed_time":0.3399881002,"remaining_time":2.178442272},
{"learn":[1728497.858],"iteration":135,"passed_time":0.3433371318,"remaining_time":2.181200602},
{"learn":[1727645.958],"iteration":136,"passed_time":0.3458118694,"remaining_time":2.178362359},
{"learn":[1724949.499],"iteration":137,"passed_time":0.3483736616,"remaining_time":2.176073162},
{"learn":[1722178.402],"iteration":138,"passed_time":0.3507913289,"remaining_time":2.172887296},
{"learn":[1718648.87],"iteration":139,"passed_time":0.3534531382,"remaining_time":2.171212135},
{"learn":[1715736.066],"iteration":140,"passed_time":0.3558367542,"remaining_time":2.167828169},
{"learn":[1713902.926],"iteration":141,"passed_time":0.3589791008,"remaining_time":2.169042736},
{"learn":[1713094.301],"iteration":142,"passed_time":0.3616292813,"remaining_time":2.167246812},
{"learn":[1711123.379],"iteration":143,"passed_time":0.3646241602,"remaining_time":2.167488064},
{"learn":[1708938.533],"iteration":144,"passed_time":0.3666183853,"remaining_time":2.161784272},
{"learn":[1705360.773],"iteration":145,"passed_time":0.3697159778,"remaining_time":2.16258524},
{"learn":[1703845.328],"iteration":146,"passed_time":0.3719416428,"remaining_time":2.158273614},
{"learn":[1702880.417],"iteration":147,"passed_time":0.373674399,"remaining_time":2.151152622},
{"learn":[1699797.136],"iteration":148,"passed_time":0.375956405,"remaining_time":2.147240944},
{"learn":[1697758.987],"iteration":149,"passed_time":0.3782526218,"remaining_time":2.143431523},
{"learn":[1697127.694],"iteration":150,"passed_time":0.3810460464,"remaining_time":2.142437705},
{"learn":[1694657.097],"iteration":151,"passed_time":0.3840099381,"remaining_time":2.142371234},
{"learn":[1692899.846],"iteration":152,"passed_time":0.3868330558,"remaining_time":2.14148757},
{"learn":[1691327.834],"iteration":153,"passed_time":0.3895825027,"remaining_time":2.140174008},
{"learn":[1689536.075],"iteration":154,"passed_time":0.3923704784,"remaining_time":2.139051963},
{"learn":[1687241.174],"iteration":155,"passed_time":0.3945902432,"remaining_time":2.134834393},
{"learn":[1684653.754],"iteration":156,"passed_time":0.3966510173,"remaining_time":2.129788584},
{"learn":[1682504.787],"iteration":157,"passed_time":0.3993388716,"remaining_time":2.128122341},
{"learn":[1679125.388],"iteration":158,"passed_time":0.4028446999,"remaining_time":2.130769765},
{"learn":[1677772.253],"iteration":159,"passed_time":0.4051811568,"remaining_time":2.127201073},
{"learn":[1675096.223],"iteration":160,"passed_time":0.4076164494,"remaining_time":2.124162739},
{"learn":[1673161.812],"iteration":161,"passed_time":0.4097325375,"remaining_time":2.119480657},
{"learn":[1672335.391],"iteration":162,"passed_time":0.4114581452,"remaining_time":2.112824954},
{"learn":[1670216.102],"iteration":163,"passed_time":0.4135872274,"remaining_time":2.10828611},
{"learn":[1667951.332],"iteration":164,"passed_time":0.4157925295,"remaining_time":2.104162195},
{"learn":[1665137.67],"iteration":165,"passed_time":0.4186993681,"remaining_time":2.103585982},
{"learn":[1663842.435],"iteration":166,"passed_time":0.4221058213,"remaining_time":2.105473947},
{"learn":[1663054.693],"iteration":167,"passed_time":0.4245204949,"remaining_time":2.102387213},
{"learn":[1662189.259],"iteration":168,"passed_time":0.4268884956,"remaining_time":2.099078934},
{"learn":[1661685.577],"iteration":169,"passed_time":0.4287208186,"remaining_time":2.09316635},
{"learn":[1659258.693],"iteration":170,"passed_time":0.4308341517,"remaining_time":2.088663812},
{"learn":[1657102.098],"iteration":171,"passed_time":0.4328734623,"remaining_time":2.083832714},
{"learn":[1655121.856],"iteration":172,"passed_time":0.4351074524,"remaining_time":2.079964527},
{"learn":[1652704.336],"iteration":173,"passed_time":0.437607404,"remaining_time":2.077377676},
{"learn":[1649957.968],"iteration":174,"passed_time":0.440150435,"remaining_time":2.074994908},
{"learn":[1649241.353],"iteration":175,"passed_time":0.4421179811,"remaining_time":2.069916002},
{"learn":[1647195.037],"iteration":176,"passed_time":0.4440149897,"remaining_time":2.064544274},
{"learn":[1646389.169],"iteration":177,"passed_time":0.446179518,"remaining_time":2.060446988},
{"learn":[1644329.493],"iteration":178,"passed_time":0.4485995004,"remaining_time":2.05754296},
{"learn":[1643642.369],"iteration":179,"passed_time":0.4506467983,"remaining_time":2.052946526},
{"learn":[1641995.569],"iteration":180,"passed_time":0.4530735032,"remaining_time":2.050095023},
{"learn":[1640729.942],"iteration":181,"passed_time":0.4555369297,"remaining_time":2.047413234},
{"learn":[1640061.931],"iteration":182,"passed_time":0.4579347261,"remaining_time":2.044440826},
{"learn":[1639426.295],"iteration":183,"passed_time":0.4600611291,"remaining_time":2.040271094},
{"learn":[1638796.464],"iteration":184,"passed_time":0.4621645891,"remaining_time":2.036022379},
{"learn":[1636436.212],"iteration":185,"passed_time":0.464200448,"remaining_time":2.031500885},
{"learn":[1634096.454],"iteration":186,"passed_time":0.4664020369,"remaining_time":2.027726503},
{"learn":[1632391.858],"iteration":187,"passed_time":0.4688734142,"remaining_time":2.025134108},
{"learn":[1629980.056],"iteration":188,"passed_time":0.4710566101,"remaining_time":2.021306406},
{"learn":[1627219.748],"iteration":189,"passed_time":0.4730662364,"remaining_time":2.016756061},
{"learn":[1624927.192],"iteration":190,"passed_time":0.4755630418,"remaining_time":2.014295816},
{"learn":[1624350.588],"iteration":191,"passed_time":0.4784602643,"remaining_time":2.013520279},
{"learn":[1621897.128],"iteration":192,"passed_time":0.480895179,"remaining_time":2.010789686},
{"learn":[1619481.515],"iteration":193,"passed_time":0.4831180183,"remaining_time":2.007181045},
{"learn":[1618940.338],"iteration":194,"passed_time":0.4852764462,"remaining_time":2.003320714},
{"learn":[1616726.482],"iteration":195,"passed_time":0.4878147427,"remaining_time":2.001035986},
{"learn":[1616205.226],"iteration":196,"passed_time":0.4898531571,"remaining_time":1.996711092},
{"learn":[1615047.565],"iteration":197,"passed_time":0.4919295366,"remaining_time":1.992563072},
{"learn":[1614236.59],"iteration":198,"passed_time":0.4939435522,"remaining_time":1.988184851},
{"learn":[1613760.89],"iteration":199,"passed_time":0.4959570872,"remaining_time":1.983828349},
{"learn":[1611858.539],"iteration":200,"passed_time":0.4986856894,"remaining_time":1.982337641},
{"learn":[1609663.992],"iteration":201,"passed_time":0.5010062302,"remaining_time":1.979222632},
{"learn":[1606980.692],"iteration":202,"passed_time":0.5033858636,"remaining_time":1.976347455},
{"learn":[1605997.498],"iteration":203,"passed_time":0.5055777622,"remaining_time":1.972744601},
{"learn":[1604487.142],"iteration":204,"passed_time":0.5076032273,"remaining_time":1.968510077},
{"learn":[1603175.021],"iteration":205,"passed_time":0.5095702092,"remaining_time":1.964071583},
{"learn":[1602713.053],"iteration":206,"passed_time":0.5113105796,"remaining_time":1.958788839},
{"learn":[1602269.822],"iteration":207,"passed_time":0.5135523134,"remaining_time":1.955449193},
{"learn":[1601109.08],"iteration":208,"passed_time":0.516185523,"remaining_time":1.953601668},
{"learn":[1599185.958],"iteration":209,"passed_time":0.5193447721,"remaining_time":1.953725571},
{"learn":[1597968.789],"iteration":210,"passed_time":0.5217502176,"remaining_time":1.950999629},
{"learn":[1595744.604],"iteration":211,"passed_time":0.5239528506,"remaining_time":1.94752286},
{"learn":[1594920.135],"iteration":212,"passed_time":0.5260780196,"remaining_time":1.943771838},
{"learn":[1593905.242],"iteration":213,"passed_time":0.5279419571,"remaining_time":1.939076534},
{"learn":[1591936.198],"iteration":214,"passed_time":0.5301467822,"remaining_time":1.935652205},
{"learn":[1590390.857],"iteration":215,"passed_time":0.5320491425,"remaining_time":1.931141332},
{"learn":[1589976.054],"iteration":216,"passed_time":0.5342892572,"remaining_time":1.927873218},
{"learn":[1587661.757],"iteration":217,"passed_time":0.5379203989,"remaining_time":1.929604367},
{"learn":[1585597.419],"iteration":218,"passed_time":0.5400209879,"remaining_time":1.925828272},
{"learn":[1584357.981],"iteration":219,"passed_time":0.5423942844,"remaining_time":1.923034281},
{"learn":[1583002.881],"iteration":220,"passed_time":0.5445045727,"remaining_time":1.919317023},
{"learn":[1582600.711],"iteration":221,"passed_time":0.5465612515,"remaining_time":1.915426368},
{"learn":[1580342.08],"iteration":222,"passed_time":0.5491427916,"remaining_time":1.913380938},
{"learn":[1578697.605],"iteration":223,"passed_time":0.5514957337,"remaining_time":1.910538792},
{"learn":[1577030.676],"iteration":224,"passed_time":0.5544273605,"remaining_time":1.909694242},
{"learn":[1575772.43],"iteration":225,"passed_time":0.5569037705,"remaining_time":1.907272205},
{"learn":[1573595.052],"iteration":226,"passed_time":0.5595186946,"remaining_time":1.90532137},
{"learn":[1572355.075],"iteration":227,"passed_time":0.5617039786,"remaining_time":1.901909962},
{"learn":[1570847.984],"iteration":228,"passed_time":0.5636458372,"remaining_time":1.897689696},
{"learn":[1569201.511],"iteration":229,"passed_time":0.5657774386,"remaining_time":1.894124468},
{"learn":[1567127.55],"iteration":230,"passed_time":0.567890885,"remaining_time":1.890511215},
{"learn":[1565367.135],"iteration":231,"passed_time":0.5700506944,"remaining_time":1.887064368},
{"learn":[1564245.639],"iteration":232,"passed_time":0.5724650066,"remaining_time":1.884466352},
{"learn":[1562483.567],"iteration":233,"passed_time":0.5751512899,"remaining_time":1.882760205},
{"learn":[1561056.49],"iteration":234,"passed_time":0.5778390227,"remaining_time":1.881050436},
{"learn":[1560164.07],"iteration":235,"passed_time":0.5800093447,"remaining_time":1.87765737},
{"learn":[1558909.106],"iteration":236,"passed_time":0.5826560741,"remaining_time":1.875808374},
{"learn":[1557528.449],"iteration":237,"passed_time":0.5850835626,"remaining_time":1.873250734},
{"learn":[1556442.13],"iteration":238,"passed_time":0.587300491,"remaining_time":1.870023739},
{"learn":[1554914.696],"iteration":239,"passed_time":0.5894060952,"remaining_time":1.866452635},
{"learn":[1553534.79],"iteration":240,"passed_time":0.5917724551,"remaining_time":1.86371491},
{"learn":[1551579.664],"iteration":241,"passed_time":0.5948259578,"remaining_time":1.863132546},
{"learn":[1551265.101],"iteration":242,"passed_time":0.597091916,"remaining_time":1.860076463},
{"learn":[1550962.005],"iteration":243,"passed_time":0.5988716707,"remaining_time":1.855520422},
{"learn":[1550147.927],"iteration":244,"passed_time":0.6010022202,"remaining_time":1.852068066},
{"learn":[1549196.215],"iteration":245,"passed_time":0.6029437148,"remaining_time":1.848046996},
{"learn":[1547402.081],"iteration":246,"passed_time":0.6049217002,"remaining_time":1.844154009},
{"learn":[1545789.003],"iteration":247,"passed_time":0.6070131408,"remaining_time":1.840620492},
{"learn":[1545028.967],"iteration":248,"passed_time":0.6090517819,"remaining_time":1.83693931},
{"learn":[1543726.932],"iteration":249,"passed_time":0.6120779038,"remaining_time":1.836233711},
{"learn":[1543166.699],"iteration":250,"passed_time":0.6144994507,"remaining_time":1.833705532},
{"learn":[1541683.807],"iteration":251,"passed_time":0.6174701692,"remaining_time":1.83280828},
{"learn":[1541032.328],"iteration":252,"passed_time":0.6199399294,"remaining_time":1.830415523},
{"learn":[1538995.412],"iteration":253,"passed_time":0.6223796403,"remaining_time":1.827933904},
{"learn":[1537267.441],"iteration":254,"passed_time":0.62461412,"remaining_time":1.824853017},
{"learn":[1536628.753],"iteration":255,"passed_time":0.6273374629,"remaining_time":1.823199501},
{"learn":[1535425.659],"iteration":256,"passed_time":0.6299529254,"remaining_time":1.821225773},
{"learn":[1534745.064],"iteration":257,"passed_time":0.6322801765,"remaining_time":1.818418182},
{"learn":[1533017.225],"iteration":258,"passed_time":0.6358036161,"remaining_time":1.819036601},
{"learn":[1531341.297],"iteration":259,"passed_time":0.6387063247,"remaining_time":1.817856463},
{"learn":[1530844.86],"iteration":260,"passed_time":0.6406371959,"remaining_time":1.813911448},
{"learn":[1530596.274],"iteration":261,"passed_time":0.6428343613,"remaining_time":1.810731903},
{"learn":[1529099.771],"iteration":262,"passed_time":0.6452609376,"remaining_time":1.808202704},
{"learn":[1527777.125],"iteration":263,"passed_time":0.6483024931,"remaining_time":1.807388769},
{"learn":[1526546.689],"iteration":264,"passed_time":0.652303186,"remaining_time":1.809218271},
{"learn":[1524784.131],"iteration":265,"passed_time":0.6560901593,"remaining_time":1.810414199},
{"learn":[1522713.396],"iteration":266,"passed_time":0.6584836126,"remaining_time":1.807747146},
{"learn":[1521006.529],"iteration":267,"passed_time":0.6607576068,"remaining_time":1.804755851},
{"learn":[1519844.761],"iteration":268,"passed_time":0.6626920973,"remaining_time":1.800847298},
{"learn":[1519022.354],"iteration":269,"passed_time":0.6647127556,"remaining_time":1.797186339},
{"learn":[1517328.205],"iteration":270,"passed_time":0.6668969999,"remaining_time":1.793977538},
{"learn":[1517096.515],"iteration":271,"passed_time":0.6694069105,"remaining_time":1.791647907},
{"learn":[1515696.792],"iteration":272,"passed_time":0.6727491857,"remaining_time":1.791533546},
{"learn":[1514244.847],"iteration":273,"passed_time":0.6751136891,"remaining_time":1.788804884},
{"learn":[1512681.395],"iteration":274,"passed_time":0.6778452398,"remaining_time":1.787046541},
{"learn":[1511362.289],"iteration":275,"passed_time":0.6804670643,"remaining_time":1.784993314},
{"learn":[1509830.171],"iteration":276,"passed_time":0.6826203602,"remaining_time":1.78171307},
{"learn":[1508653.379],"iteration":277,"passed_time":0.6845123228,"remaining_time":1.77776222},
{"learn":[1507940.387],"iteration":278,"passed_time":0.6868733236,"remaining_time":1.77503823},
{"learn":[1506729.461],"iteration":279,"passed_time":0.6898373926,"remaining_time":1.773867581},
{"learn":[1506182.118],"iteration":280,"passed_time":0.69231044,"remaining_time":1.771427781},
{"learn":[1505237.354],"iteration":281,"passed_time":0.6944355431,"remaining_time":1.768101844},
{"learn":[1503678.971],"iteration":282,"passed_time":0.6965344267,"remaining_time":1.764717965},
{"learn":[1502797.76],"iteration":283,"passed_time":0.6986799178,"remaining_time":1.761460638},
{"learn":[1502593.23],"iteration":284,"passed_time":0.7005318573,"remaining_time":1.75747466},
{"learn":[1501358.287],"iteration":285,"passed_time":0.7026427984,"remaining_time":1.754150203},
{"learn":[1500518.166],"iteration":286,"passed_time":0.7048011544,"remaining_time":1.750951997},
{"learn":[1499924.944],"iteration":287,"passed_time":0.7074989993,"remaining_time":1.749094748},
{"learn":[1499173.481],"iteration":288,"passed_time":0.7108032894,"remaining_time":1.748723663},
{"learn":[1497408.743],"iteration":289,"passed_time":0.7134219148,"remaining_time":1.746653654},
{"learn":[1496374.901],"iteration":290,"passed_time":0.7157920051,"remaining_time":1.743974336},
{"learn":[1494906.198],"iteration":291,"passed_time":0.7177385721,"remaining_time":1.740270237},
{"learn":[1494310.882],"iteration":292,"passed_time":0.7198713886,"remaining_time":1.737027549},
{"learn":[1493046.153],"iteration":293,"passed_time":0.7219581903,"remaining_time":1.733681913},
{"learn":[1491914.471],"iteration":294,"passed_time":0.7240034382,"remaining_time":1.730245505},
{"learn":[1491084.177],"iteration":295,"passed_time":0.7264037686,"remaining_time":1.727663017},
{"learn":[1490903.598],"iteration":296,"passed_time":0.7286697662,"remaining_time":1.72476379},
{"learn":[1489674.522],"iteration":297,"passed_time":0.7311127644,"remaining_time":1.722285774},
{"learn":[1489109.502],"iteration":298,"passed_time":0.7330595591,"remaining_time":1.718644652},
{"learn":[1488297.113],"iteration":299,"passed_time":0.7354041993,"remaining_time":1.715943132},
{"learn":[1486907.875],"iteration":300,"passed_time":0.7376199763,"remaining_time":1.712944729},
{"learn":[1486219.958],"iteration":301,"passed_time":0.7396862602,"remaining_time":1.709605992},
{"learn":[1485538.263],"iteration":302,"passed_time":0.7421999208,"remaining_time":1.707304768},
{"learn":[1484375.164],"iteration":303,"passed_time":0.7447984842,"remaining_time":1.70519653},
{"learn":[1483657.171],"iteration":304,"passed_time":0.7476321006,"remaining_time":1.703620688},
{"learn":[1483164.671],"iteration":305,"passed_time":0.7500375761,"remaining_time":1.701065614},
{"learn":[1481294.263],"iteration":306,"passed_time":0.7522858302,"remaining_time":1.698156613},
{"learn":[1480429.357],"iteration":307,"passed_time":0.7546017405,"remaining_time":1.695403911},
{"learn":[1479263.53],"iteration":308,"passed_time":0.7566859374,"remaining_time":1.692135866},
{"learn":[1478974.279],"iteration":309,"passed_time":0.7587254253,"remaining_time":1.688775947},
{"learn":[1478254.472],"iteration":310,"passed_time":0.7608507784,"remaining_time":1.685614747},
{"learn":[1477606.453],"iteration":311,"passed_time":0.7627968199,"remaining_time":1.682064782},
{"learn":[1476612.194],"iteration":312,"passed_time":0.7653788206,"remaining_time":1.679920926},
{"learn":[1475816.086],"iteration":313,"passed_time":0.7679614242,"remaining_time":1.677775596},
{"learn":[1474377.156],"iteration":314,"passed_time":0.7703817041,"remaining_time":1.675274499},
{"learn":[1473037.877],"iteration":315,"passed_time":0.7731009868,"remaining_time":1.673421123},
{"learn":[1472000.909],"iteration":316,"passed_time":0.7755600085,"remaining_time":1.671001533},
{"learn":[1470856.229],"iteration":317,"passed_time":0.7780894296,"remaining_time":1.668732676},
{"learn":[1470180.506],"iteration":318,"passed_time":0.7800458136,"remaining_time":1.665238868},
{"learn":[1468908.39],"iteration":319,"passed_time":0.7823248601,"remaining_time":1.662440328},
{"learn":[1468115.831],"iteration":320,"passed_time":0.7848938128,"remaining_time":1.660258252},
{"learn":[1466929.223],"iteration":321,"passed_time":0.7880141478,"remaining_time":1.659234758},
{"learn":[1466453.881],"iteration":322,"passed_time":0.7900190283,"remaining_time":1.655860316},
{"learn":[1465809.442],"iteration":323,"passed_time":0.7921993248,"remaining_time":1.65286032},
{"learn":[1465226.843],"iteration":324,"passed_time":0.7944653876,"remaining_time":1.650043497},
{"learn":[1464588.729],"iteration":325,"passed_time":0.7966030917,"remaining_time":1.646964674},
{"learn":[1463865.228],"iteration":326,"passed_time":0.7992749056,"remaining_time":1.644990861},
{"learn":[1462711.127],"iteration":327,"passed_time":0.8013662348,"remaining_time":1.641823505},
{"learn":[1461629.476],"iteration":328,"passed_time":0.8039123835,"remaining_time":1.639590302},
{"learn":[1461434.744],"iteration":329,"passed_time":0.8069649784,"remaining_time":1.638383441},
{"learn":[1460585.615],"iteration":330,"passed_time":0.8098904266,"remaining_time":1.636908445},
{"learn":[1459339.527],"iteration":331,"passed_time":0.8123096839,"remaining_time":1.634406231},
{"learn":[1457819.85],"iteration":332,"passed_time":0.8142795416,"remaining_time":1.631004367},
{"learn":[1456566.408],"iteration":333,"passed_time":0.8164689464,"remaining_time":1.628048857},
{"learn":[1455382.324],"iteration":334,"passed_time":0.8188736061,"remaining_time":1.625525218},
{"learn":[1454775.741],"iteration":335,"passed_time":0.8209610217,"remaining_time":1.622375352},
{"learn":[1453761.637],"iteration":336,"passed_time":0.8236307837,"remaining_time":1.620377477},
{"learn":[1452649.66],"iteration":337,"passed_time":0.8263732837,"remaining_time":1.618518088},
{"learn":[1451988.511],"iteration":338,"passed_time":0.8285149074,"remaining_time":1.61548187},
{"learn":[1451340.825],"iteration":339,"passed_time":0.8308540977,"remaining_time":1.612834425},
{"learn":[1450609.533],"iteration":340,"passed_time":0.8331172392,"remaining_time":1.61004182},
{"learn":[1449252.973],"iteration":341,"passed_time":0.8357321549,"remaining_time":1.607929117},
{"learn":[1449126.429],"iteration":342,"passed_time":0.8376971595,"remaining_time":1.604568612},
{"learn":[1448433.931],"iteration":343,"passed_time":0.8401216672,"remaining_time":1.602092482},
{"learn":[1447660.29],"iteration":344,"passed_time":0.8428662371,"remaining_time":1.600224305},
{"learn":[1447345.663],"iteration":345,"passed_time":0.84537752,"remaining_time":1.59791011},
{"learn":[1447002.203],"iteration":346,"passed_time":0.8473777809,"remaining_time":1.594633115},
{"learn":[1445290.696],"iteration":347,"passed_time":0.8498333856,"remaining_time":1.592216573},
{"learn":[1444712.088],"iteration":348,"passed_time":0.853194929,"remaining_time":1.591489681},
{"learn":[1443739.097],"iteration":349,"passed_time":0.855469927,"remaining_time":1.588729865},
{"learn":[1443376.026],"iteration":350,"passed_time":0.8573278668,"remaining_time":1.585201668},
{"learn":[1442648.891],"iteration":351,"passed_time":0.8595025432,"remaining_time":1.582266045},
{"learn":[1441147.067],"iteration":352,"passed_time":0.8623622172,"remaining_time":1.580590239},
{"learn":[1439622.982],"iteration":353,"passed_time":0.8652283113,"remaining_time":1.578919461},
{"learn":[1438686.599],"iteration":354,"passed_time":0.8674784584,"remaining_time":1.576122833},
{"learn":[1438297.041],"iteration":355,"passed_time":0.8699996984,"remaining_time":1.573819679},
{"learn":[1437772.067],"iteration":356,"passed_time":0.8730830854,"remaining_time":1.572527798},
{"learn":[1436411.454],"iteration":357,"passed_time":0.8752826166,"remaining_time":1.569640893},
{"learn":[1435384.701],"iteration":358,"passed_time":0.8772575053,"remaining_time":1.566356716},
{"learn":[1434292.718],"iteration":359,"passed_time":0.879478978,"remaining_time":1.563518183},
{"learn":[1433548.056],"iteration":360,"passed_time":0.8820211186,"remaining_time":1.561250678},
{"learn":[1432397.614],"iteration":361,"passed_time":0.8847654738,"remaining_time":1.559338045},
{"learn":[1431823.674],"iteration":362,"passed_time":0.8870378476,"remaining_time":1.556592587},
{"learn":[1431314.172],"iteration":363,"passed_time":0.8892723961,"remaining_time":1.553783637},
{"learn":[1430373.152],"iteration":364,"passed_time":0.8912801698,"remaining_time":1.550583309},
{"learn":[1429131.911],"iteration":365,"passed_time":0.8933632821,"remaining_time":1.547520002},
{"learn":[1428258.399],"iteration":366,"passed_time":0.8955366895,"remaining_time":1.544617778},
{"learn":[1427116.726],"iteration":367,"passed_time":0.8975923422,"remaining_time":1.541517283},
{"learn":[1426417.801],"iteration":368,"passed_time":0.9005400572,"remaining_time":1.539947903},
{"learn":[1425411.711],"iteration":369,"passed_time":0.9045233697,"remaining_time":1.540134386},
{"learn":[1424525.39],"iteration":370,"passed_time":0.9066958127,"remaining_time":1.537228211},
{"learn":[1423450.587],"iteration":371,"passed_time":0.9090998493,"remaining_time":1.53471695},
{"learn":[1422766.172],"iteration":372,"passed_time":0.9111252741,"remaining_time":1.531569831},
{"learn":[1422191.561],"iteration":373,"passed_time":0.9135114726,"remaining_time":1.529032572},
{"learn":[1421667.33],"iteration":374,"passed_time":0.9157999379,"remaining_time":1.52633323},
{"learn":[1420528.624],"iteration":375,"passed_time":0.9186399476,"remaining_time":1.524551402},
{"learn":[1419193.91],"iteration":376,"passed_time":0.9212422911,"remaining_time":1.522371213},
{"learn":[1418570.695],"iteration":377,"passed_time":0.9240375948,"remaining_time":1.520506307},
{"learn":[1418211.78],"iteration":378,"passed_time":0.9261035954,"remaining_time":1.517441511},
{"learn":[1417493.824],"iteration":379,"passed_time":0.9284238188,"remaining_time":1.514796757},
{"learn":[1416720.113],"iteration":380,"passed_time":0.9307195617,"remaining_time":1.512113934},
{"learn":[1415873.199],"iteration":381,"passed_time":0.9332574526,"remaining_time":1.509824884},
{"learn":[1415310.263],"iteration":382,"passed_time":0.9367705979,"remaining_time":1.509105637},
{"learn":[1414651.498],"iteration":383,"passed_time":0.9399383314,"remaining_time":1.50781774},
{"learn":[1413724.196],"iteration":384,"passed_time":0.9441938285,"remaining_time":1.508257674},
{"learn":[1412383.803],"iteration":385,"passed_time":0.9465722665,"remaining_time":1.505687491},
{"learn":[1411866.446],"iteration":386,"passed_time":0.9487773481,"remaining_time":1.502843706},
{"learn":[1410523.729],"iteration":387,"passed_time":0.9513874437,"remaining_time":1.50064205},
{"learn":[1409966.556],"iteration":388,"passed_time":0.9534456463,"remaining_time":1.497571439},
{"learn":[1409591.589],"iteration":389,"passed_time":0.955672775,"remaining_time":1.494770238},
{"learn":[1409135.003],"iteration":390,"passed_time":0.9583967971,"remaining_time":1.492745906},
{"learn":[1407694.334],"iteration":391,"passed_time":0.9617390907,"remaining_time":1.491676957},
{"learn":[1407227.643],"iteration":392,"passed_time":0.964185733,"remaining_time":1.489213079},
{"learn":[1405993.453],"iteration":393,"passed_time":0.9672398865,"remaining_time":1.487683683},
{"learn":[1404935.509],"iteration":394,"passed_time":0.9701164235,"remaining_time":1.485874522},
{"learn":[1404424.358],"iteration":395,"passed_time":0.9722894967,"remaining_time":1.48298701},
{"learn":[1404244.04],"iteration":396,"passed_time":0.9742336924,"remaining_time":1.479755457},
{"learn":[1403373.977],"iteration":397,"passed_time":0.976658564,"remaining_time":1.477257426},
{"learn":[1402762.819],"iteration":398,"passed_time":0.979729743,"remaining_time":1.475733272},
{"learn":[1401857.472],"iteration":399,"passed_time":0.9828781937,"remaining_time":1.474317291},
{"learn":[1401070.536],"iteration":400,"passed_time":0.9851876616,"remaining_time":1.471639425},
{"learn":[1400305.297],"iteration":401,"passed_time":0.9871236543,"remaining_time":1.468407824},
{"learn":[1399436.095],"iteration":402,"passed_time":0.9892470546,"remaining_time":1.465460277},
{"learn":[1398391.138],"iteration":403,"passed_time":0.9914022379,"remaining_time":1.462563698},
{"learn":[1397283.728],"iteration":404,"passed_time":0.9938066931,"remaining_time":1.460036994},
{"learn":[1396523.587],"iteration":405,"passed_time":0.9967188127,"remaining_time":1.458253632},
{"learn":[1395474.411],"iteration":406,"passed_time":1.000739287,"remaining_time":1.4580796},
{"learn":[1394772.956],"iteration":407,"passed_time":1.003116458,"remaining_time":1.455502311},
{"learn":[1393831.078],"iteration":408,"passed_time":1.00526721,"remaining_time":1.45259883},
{"learn":[1393223.968],"iteration":409,"passed_time":1.007883046,"remaining_time":1.450368286},
{"learn":[1392403.053],"iteration":410,"passed_time":1.01031518,"remaining_time":1.447872606},
{"learn":[1391986.144],"iteration":411,"passed_time":1.012596482,"remaining_time":1.445161969},
{"learn":[1391103.558],"iteration":412,"passed_time":1.015258534,"remaining_time":1.442994575},
{"learn":[1390335.853],"iteration":413,"passed_time":1.018701811,"remaining_time":1.441930583},
{"learn":[1389488.521],"iteration":414,"passed_time":1.020749327,"remaining_time":1.438887606},
{"learn":[1388803.521],"iteration":415,"passed_time":1.022850212,"remaining_time":1.435924336},
{"learn":[1387902.21],"iteration":416,"passed_time":1.025198862,"remaining_time":1.433311599},
{"learn":[1386828.967],"iteration":417,"passed_time":1.027269189,"remaining_time":1.430312603},
{"learn":[1386260.472],"iteration":418,"passed_time":1.029435624,"remaining_time":1.427451307},
{"learn":[1385643.788],"iteration":419,"passed_time":1.032027176,"remaining_time":1.425180385},
{"learn":[1385018.622],"iteration":420,"passed_time":1.035288707,"remaining_time":1.423829362},
{"learn":[1384765.314],"iteration":421,"passed_time":1.037680635,"remaining_time":1.421278216},
{"learn":[1384012.853],"iteration":422,"passed_time":1.040123979,"remaining_time":1.418797957},
{"learn":[1383215.181],"iteration":423,"passed_time":1.042321914,"remaining_time":1.415984487},
{"learn":[1382707.133],"iteration":424,"passed_time":1.044338379,"remaining_time":1.412928394},
{"learn":[1382472.541],"iteration":425,"passed_time":1.046164683,"remaining_time":1.409620958},
{"learn":[1381962.094],"iteration":426,"passed_time":1.047980712,"remaining_time":1.406306669},
{"learn":[1381273.896],"iteration":427,"passed_time":1.050215356,"remaining_time":1.403558841},
{"learn":[1381120.182],"iteration":428,"passed_time":1.052308256,"remaining_time":1.400624742},
{"learn":[1380613.383],"iteration":429,"passed_time":1.054653069,"remaining_time":1.398028487},
{"learn":[1379892.026],"iteration":430,"passed_time":1.057973977,"remaining_time":1.396722026},
{"learn":[1379446.078],"iteration":431,"passed_time":1.060240304,"remaining_time":1.394019659},
{"learn":[1378678.53],"iteration":432,"passed_time":1.063097256,"remaining_time":1.392092711},
{"learn":[1378010.261],"iteration":433,"passed_time":1.065441809,"remaining_time":1.389493235},
{"learn":[1377781.824],"iteration":434,"passed_time":1.067590277,"remaining_time":1.386640244},
{"learn":[1376947.292],"iteration":435,"passed_time":1.069478186,"remaining_time":1.383453433},
{"learn":[1376503.907],"iteration":436,"passed_time":1.071633445,"remaining_time":1.380617002},
{"learn":[1376369.489],"iteration":437,"passed_time":1.074154803,"remaining_time":1.378253423},
{"learn":[1375517.331],"iteration":438,"passed_time":1.077386277,"remaining_time":1.376796586},
{"learn":[1374594.97],"iteration":439,"passed_time":1.080115944,"remaining_time":1.37469302},
{"learn":[1373528.715],"iteration":440,"passed_time":1.083290172,"remaining_time":1.373150128},
{"learn":[1372984.512],"iteration":441,"passed_time":1.085544303,"remaining_time":1.370438282},
{"learn":[1372451.803],"iteration":442,"passed_time":1.087523022,"remaining_time":1.36738222},
{"learn":[1371933.248],"iteration":443,"passed_time":1.089614568,"remaining_time":1.364472297},
{"learn":[1371177.646],"iteration":444,"passed_time":1.094200221,"remaining_time":1.36467668},
{"learn":[1370107],"iteration":445,"passed_time":1.097972839,"remaining_time":1.36384967},
{"learn":[1369035.756],"iteration":446,"passed_time":1.100892971,"remaining_time":1.361954838},
{"learn":[1368399.929],"iteration":447,"passed_time":1.104234369,"remaining_time":1.36057449},
{"learn":[1367783.946],"iteration":448,"passed_time":1.108332582,"remaining_time":1.360114149},
{"learn":[1367137.068],"iteration":449,"passed_time":1.110583327,"remaining_time":1.357379621},
{"learn":[1366473.988],"iteration":450,"passed_time":1.113114779,"remaining_time":1.354988944},
{"learn":[1365751.84],"iteration":451,"passed_time":1.115689359,"remaining_time":1.352649931},
{"learn":[1365080.727],"iteration":452,"passed_time":1.117830342,"remaining_time":1.349786307},
{"learn":[1364292.726],"iteration":453,"passed_time":1.120347334,"remaining_time":1.347378072},
{"learn":[1363436.164],"iteration":454,"passed_time":1.12262014,"remaining_time":1.344676871},
{"learn":[1362796.127],"iteration":455,"passed_time":1.126435096,"remaining_time":1.343817307},
{"learn":[1361770.268],"iteration":456,"passed_time":1.128749386,"remaining_time":1.341161744},
{"learn":[1361057.05],"iteration":457,"passed_time":1.132139799,"remaining_time":1.339781159},
{"learn":[1360088.013],"iteration":458,"passed_time":1.135025391,"remaining_time":1.337796812},
{"learn":[1359238.47],"iteration":459,"passed_time":1.137242173,"remaining_time":1.335023421},
{"learn":[1358621.39],"iteration":460,"passed_time":1.139952575,"remaining_time":1.332829583},
{"learn":[1358311.247],"iteration":461,"passed_time":1.141825117,"remaining_time":1.329657821},
{"learn":[1357817.679],"iteration":462,"passed_time":1.144088889,"remaining_time":1.326945429},
{"learn":[1356856.837],"iteration":463,"passed_time":1.146237729,"remaining_time":1.324102204},
{"learn":[1356445.811],"iteration":464,"passed_time":1.14821107,"remaining_time":1.321060049},
{"learn":[1355138.018],"iteration":465,"passed_time":1.150851498,"remaining_time":1.31878691},
{"learn":[1354597.003],"iteration":466,"passed_time":1.153883344,"remaining_time":1.316958934},
{"learn":[1354030.276],"iteration":467,"passed_time":1.156729216,"remaining_time":1.314914408},
{"learn":[1353575.413],"iteration":468,"passed_time":1.159267566,"remaining_time":1.312518289},
{"learn":[1352885.978],"iteration":469,"passed_time":1.161648352,"remaining_time":1.309943887},
{"learn":[1352357.316],"iteration":470,"passed_time":1.163774523,"remaining_time":1.307084337},
{"learn":[1352190.46],"iteration":471,"passed_time":1.165620299,"remaining_time":1.303914233},
{"learn":[1351544.095],"iteration":472,"passed_time":1.16765213,"remaining_time":1.300957025},
{"learn":[1350788.681],"iteration":473,"passed_time":1.170430799,"remaining_time":1.29883249},
{"learn":[1350379.539],"iteration":474,"passed_time":1.173319375,"remaining_time":1.296826677},
{"learn":[1349718.074],"iteration":475,"passed_time":1.175755397,"remaining_time":1.294318967},
{"learn":[1348958.418],"iteration":476,"passed_time":1.178213049,"remaining_time":1.291835272},
{"learn":[1348314.092],"iteration":477,"passed_time":1.180168288,"remaining_time":1.288803026},
{"learn":[1348163.596],"iteration":478,"passed_time":1.181989254,"remaining_time":1.285629231},
{"learn":[1347303.406],"iteration":479,"passed_time":1.184138215,"remaining_time":1.2828164},
{"learn":[1346709.986],"iteration":480,"passed_time":1.186542177,"remaining_time":1.280281476},
{"learn":[1346042.286],"iteration":481,"passed_time":1.189328093,"remaining_time":1.278157577},
{"learn":[1345338.307],"iteration":482,"passed_time":1.192933872,"remaining_time":1.276908513},
{"learn":[1344935.927],"iteration":483,"passed_time":1.194977077,"remaining_time":1.273983826},
{"learn":[1344655.897],"iteration":484,"passed_time":1.197185111,"remaining_time":1.271237799},
{"learn":[1343372.559],"iteration":485,"passed_time":1.199181471,"remaining_time":1.268270115},
{"learn":[1342707.967],"iteration":486,"passed_time":1.201125872,"remaining_time":1.265251689},
{"learn":[1342246.663],"iteration":487,"passed_time":1.203409569,"remaining_time":1.262593646},
{"learn":[1341592.764],"iteration":488,"passed_time":1.205398343,"remaining_time":1.259628943},
{"learn":[1341022.421],"iteration":489,"passed_time":1.208146015,"remaining_time":1.257458097},
{"learn":[1340246.129],"iteration":490,"passed_time":1.210837561,"remaining_time":1.255226718},
{"learn":[1340115.518],"iteration":491,"passed_time":1.213078506,"remaining_time":1.252528214},
{"learn":[1339548.796],"iteration":492,"passed_time":1.215152357,"remaining_time":1.249659726},
{"learn":[1338671.179],"iteration":493,"passed_time":1.217475006,"remaining_time":1.247049298},
{"learn":[1338053.98],"iteration":494,"passed_time":1.220221178,"remaining_time":1.244872111},
{"learn":[1337548.597],"iteration":495,"passed_time":1.222425333,"remaining_time":1.242141871},
{"learn":[1337473.991],"iteration":496,"passed_time":1.22448812,"remaining_time":1.239270673},
{"learn":[1336938.943],"iteration":497,"passed_time":1.227359517,"remaining_time":1.237217826},
{"learn":[1336351.44],"iteration":498,"passed_time":1.230718464,"remaining_time":1.235651203},
{"learn":[1335991.29],"iteration":499,"passed_time":1.232786214,"remaining_time":1.232786214},
{"learn":[1335558.788],"iteration":500,"passed_time":1.235707392,"remaining_time":1.230774429},
{"learn":[1335034.555],"iteration":501,"passed_time":1.239514541,"remaining_time":1.229637932},
{"learn":[1334753.25],"iteration":502,"passed_time":1.242703975,"remaining_time":1.227880469},
{"learn":[1334628.443],"iteration":503,"passed_time":1.246918168,"remaining_time":1.227125816},
{"learn":[1333744.964],"iteration":504,"passed_time":1.249623732,"remaining_time":1.224878708},
{"learn":[1333092.486],"iteration":505,"passed_time":1.252463735,"remaining_time":1.222761038},
{"learn":[1332519.287],"iteration":506,"passed_time":1.254931759,"remaining_time":1.220278811},
{"learn":[1331460.639],"iteration":507,"passed_time":1.257260972,"remaining_time":1.217662202},
{"learn":[1330802.982],"iteration":508,"passed_time":1.259752584,"remaining_time":1.215203376},
{"learn":[1330436.089],"iteration":509,"passed_time":1.261637647,"remaining_time":1.212161661},
{"learn":[1329901.237],"iteration":510,"passed_time":1.263978017,"remaining_time":1.209560176},
{"learn":[1329341.263],"iteration":511,"passed_time":1.266656309,"remaining_time":1.207281794},
{"learn":[1328980.259],"iteration":512,"passed_time":1.269414961,"remaining_time":1.20507814},
{"learn":[1328405.746],"iteration":513,"passed_time":1.271818016,"remaining_time":1.202536101},
{"learn":[1327844.842],"iteration":514,"passed_time":1.274262577,"remaining_time":1.200033689},
{"learn":[1327374.277],"iteration":515,"passed_time":1.276262915,"remaining_time":1.197114827},
{"learn":[1326850.264],"iteration":516,"passed_time":1.278202056,"remaining_time":1.194142346},
{"learn":[1326742.506],"iteration":517,"passed_time":1.279999274,"remaining_time":1.191041795},
{"learn":[1326341.884],"iteration":518,"passed_time":1.28205979,"remaining_time":1.188190287},
{"learn":[1326007.426],"iteration":519,"passed_time":1.284469432,"remaining_time":1.185664091},
{"learn":[1325896.583],"iteration":520,"passed_time":1.287429319,"remaining_time":1.18364423},
{"learn":[1324884.639],"iteration":521,"passed_time":1.290901091,"remaining_time":1.182089505},
{"learn":[1323887.464],"iteration":522,"passed_time":1.293445434,"remaining_time":1.179681591},
{"learn":[1323582.675],"iteration":523,"passed_time":1.29577798,"remaining_time":1.177080761},
{"learn":[1323168.823],"iteration":524,"passed_time":1.298312306,"remaining_time":1.174663515},
{"learn":[1322731.311],"iteration":525,"passed_time":1.301356284,"remaining_time":1.172705092},
{"learn":[1322200.147],"iteration":526,"passed_time":1.303874356,"remaining_time":1.170270532},
{"learn":[1321582.25],"iteration":527,"passed_time":1.306514536,"remaining_time":1.167944812},
{"learn":[1321169.571],"iteration":528,"passed_time":1.308964334,"remaining_time":1.165448395},
{"learn":[1320788.608],"iteration":529,"passed_time":1.311041048,"remaining_time":1.162621306},
{"learn":[1319986.622],"iteration":530,"passed_time":1.313257019,"remaining_time":1.159920041},
{"learn":[1319654.881],"iteration":531,"passed_time":1.315507651,"remaining_time":1.157251092},
{"learn":[1319416.426],"iteration":532,"passed_time":1.317489975,"remaining_time":1.154348627},
{"learn":[1318539.752],"iteration":533,"passed_time":1.320292115,"remaining_time":1.152165029},
{"learn":[1317887.822],"iteration":534,"passed_time":1.3232875,"remaining_time":1.15014708},
{"learn":[1317462.231],"iteration":535,"passed_time":1.325777716,"remaining_time":1.147688172},
{"learn":[1317170.811],"iteration":536,"passed_time":1.32810275,"remaining_time":1.145086729},
{"learn":[1316721.762],"iteration":537,"passed_time":1.330133292,"remaining_time":1.142233422},
{"learn":[1316293.299],"iteration":538,"passed_time":1.333280274,"remaining_time":1.140338045},
{"learn":[1315864.947],"iteration":539,"passed_time":1.336827169,"remaining_time":1.138778699},
{"learn":[1315443.852],"iteration":540,"passed_time":1.339054109,"remaining_time":1.136092118},
{"learn":[1315336.117],"iteration":541,"passed_time":1.34086923,"remaining_time":1.133059238},
{"learn":[1314947.903],"iteration":542,"passed_time":1.343379389,"remaining_time":1.130615803},
{"learn":[1314080.01],"iteration":543,"passed_time":1.346172984,"remaining_time":1.128409707},
{"learn":[1313664.524],"iteration":544,"passed_time":1.348719955,"remaining_time":1.125995559},
{"learn":[1313575.605],"iteration":545,"passed_time":1.350926295,"remaining_time":1.123297688},
{"learn":[1312786.403],"iteration":546,"passed_time":1.353917515,"remaining_time":1.121251616},
{"learn":[1312520.241],"iteration":547,"passed_time":1.356102839,"remaining_time":1.118537378},
{"learn":[1311617.127],"iteration":548,"passed_time":1.358392548,"remaining_time":1.115910818},
{"learn":[1311302.316],"iteration":549,"passed_time":1.360270114,"remaining_time":1.112948275},
{"learn":[1310774.798],"iteration":550,"passed_time":1.363234769,"remaining_time":1.110875519},
{"learn":[1310143.296],"iteration":551,"passed_time":1.366271329,"remaining_time":1.10885789},
{"learn":[1309454.026],"iteration":552,"passed_time":1.36845735,"remaining_time":1.10614907},
{"learn":[1309148.783],"iteration":553,"passed_time":1.37061276,"remaining_time":1.103417493},
{"learn":[1308630.766],"iteration":554,"passed_time":1.372703072,"remaining_time":1.100635797},
{"learn":[1308371.046],"iteration":555,"passed_time":1.374629439,"remaining_time":1.097725667},
{"learn":[1308209.249],"iteration":556,"passed_time":1.376660445,"remaining_time":1.094902293},
{"learn":[1307498.731],"iteration":557,"passed_time":1.3789154,"remaining_time":1.092259152},
{"learn":[1307139.472],"iteration":558,"passed_time":1.381629814,"remaining_time":1.089979871},
{"learn":[1306657.356],"iteration":559,"passed_time":1.384871482,"remaining_time":1.088113307},
{"learn":[1306255.688],"iteration":560,"passed_time":1.388254563,"remaining_time":1.086352501},
{"learn":[1306130.746],"iteration":561,"passed_time":1.390407723,"remaining_time":1.083627372},
{"learn":[1305666.341],"iteration":562,"passed_time":1.392452296,"remaining_time":1.080819988},
{"learn":[1304802.472],"iteration":563,"passed_time":1.394490859,"remaining_time":1.078010664},
{"learn":[1304413.13],"iteration":564,"passed_time":1.396780087,"remaining_time":1.075397058},
{"learn":[1304125.698],"iteration":565,"passed_time":1.398951463,"remaining_time":1.072694231},
{"learn":[1303435.523],"iteration":566,"passed_time":1.402247805,"remaining_time":1.07085238},
{"learn":[1303047.75],"iteration":567,"passed_time":1.404727373,"remaining_time":1.0683842},
{"learn":[1302387.889],"iteration":568,"passed_time":1.406790415,"remaining_time":1.065600472},
{"learn":[1302024.779],"iteration":569,"passed_time":1.409188321,"remaining_time":1.063071891},
{"learn":[1300989.217],"iteration":570,"passed_time":1.41155913,"remaining_time":1.060523409},
{"learn":[1300192.096],"iteration":571,"passed_time":1.414171087,"remaining_time":1.058155988},
{"learn":[1299554.119],"iteration":572,"passed_time":1.416749648,"remaining_time":1.055762827},
{"learn":[1299091.614],"iteration":573,"passed_time":1.420673386,"remaining_time":1.054367356},
{"learn":[1298624.63],"iteration":574,"passed_time":1.423305073,"remaining_time":1.052008097},
{"learn":[1298289.213],"iteration":575,"passed_time":1.425482877,"remaining_time":1.049313784},
{"learn":[1298051.835],"iteration":576,"passed_time":1.427592449,"remaining_time":1.046571241},
{"learn":[1297335.405],"iteration":577,"passed_time":1.430244817,"remaining_time":1.044227185},
{"learn":[1296816.717],"iteration":578,"passed_time":1.432858375,"remaining_time":1.041853844},
{"learn":[1296269.891],"iteration":579,"passed_time":1.435346187,"remaining_time":1.039388619},
{"learn":[1295498.37],"iteration":580,"passed_time":1.43749256,"remaining_time":1.036677078},
{"learn":[1294689.513],"iteration":581,"passed_time":1.440882599,"remaining_time":1.034860698},
{"learn":[1294320.092],"iteration":582,"passed_time":1.443328892,"remaining_time":1.03236389},
{"learn":[1293733.727],"iteration":583,"passed_time":1.446021854,"remaining_time":1.030042964},
{"learn":[1293450.237],"iteration":584,"passed_time":1.448491534,"remaining_time":1.02756237},
{"learn":[1292780.133],"iteration":585,"passed_time":1.451419536,"remaining_time":1.025405611},
{"learn":[1292278.866],"iteration":586,"passed_time":1.453439635,"remaining_time":1.022607443},
{"learn":[1292060.948],"iteration":587,"passed_time":1.455501499,"remaining_time":1.019841187},
{"learn":[1291459.268],"iteration":588,"passed_time":1.458161587,"remaining_time":1.017494758},
{"learn":[1291171.714],"iteration":589,"passed_time":1.461360805,"remaining_time":1.015521915},
{"learn":[1290677.764],"iteration":590,"passed_time":1.463785388,"remaining_time":1.013008839},
{"learn":[1290105.429],"iteration":591,"passed_time":1.46600208,"remaining_time":1.010352785},
{"learn":[1289572.002],"iteration":592,"passed_time":1.468687939,"remaining_time":1.008020221},
{"learn":[1288961.308],"iteration":593,"passed_time":1.470662691,"remaining_time":1.005200425},
{"learn":[1288373.134],"iteration":594,"passed_time":1.472682577,"remaining_time":1.002414191},
{"learn":[1287944.784],"iteration":595,"passed_time":1.474796499,"remaining_time":0.9996942711},
{"learn":[1287600.64],"iteration":596,"passed_time":1.477547269,"remaining_time":0.9974062805},
{"learn":[1287011.256],"iteration":597,"passed_time":1.481035188,"remaining_time":0.9956122833},
{"learn":[1286613.531],"iteration":598,"passed_time":1.484091993,"remaining_time":0.9935240223},
{"learn":[1286238.798],"iteration":599,"passed_time":1.486345159,"remaining_time":0.9908967725},
{"learn":[1286139.999],"iteration":600,"passed_time":1.488615374,"remaining_time":0.9882820872},
{"learn":[1285774.076],"iteration":601,"passed_time":1.490883719,"remaining_time":0.9856673093},
{"learn":[1285688.022],"iteration":602,"passed_time":1.493065922,"remaining_time":0.9829969668},
{"learn":[1285416.206],"iteration":603,"passed_time":1.495158751,"remaining_time":0.9802696447},
{"learn":[1285126.785],"iteration":604,"passed_time":1.49820549,"remaining_time":0.9781672209},
{"learn":[1284678.657],"iteration":605,"passed_time":1.500771418,"remaining_time":0.9757490737},
{"learn":[1284189.361],"iteration":606,"passed_time":1.503080744,"remaining_time":0.9731643035},
{"learn":[1283759.677],"iteration":607,"passed_time":1.505512776,"remaining_time":0.9706595532},
{"learn":[1283608.168],"iteration":608,"passed_time":1.507316696,"remaining_time":0.9677517704},
{"learn":[1283136.826],"iteration":609,"passed_time":1.509817024,"remaining_time":0.9652928511},
{"learn":[1282799.929],"iteration":610,"passed_time":1.51201298,"remaining_time":0.9626400151},
{"learn":[1282412.32],"iteration":611,"passed_time":1.514285218,"remaining_time":0.9600370339},
{"learn":[1281954.997],"iteration":612,"passed_time":1.517489835,"remaining_time":0.9580237619},
{"learn":[1281662.828],"iteration":613,"passed_time":1.519824346,"remaining_time":0.9554596052},
{"learn":[1281169.043],"iteration":614,"passed_time":1.52209623,"remaining_time":0.9528569897},
{"learn":[1280912.707],"iteration":615,"passed_time":1.524343528,"remaining_time":0.9502401216},
{"learn":[1280533.765],"iteration":616,"passed_time":1.526541089,"remaining_time":0.9475935774},
{"learn":[1280144.725],"iteration":617,"passed_time":1.528604019,"remaining_time":0.9448652674},
{"learn":[1279829.596],"iteration":618,"passed_time":1.530670617,"remaining_time":0.9421413655},
{"learn":[1279199.546],"iteration":619,"passed_time":1.532777757,"remaining_time":0.9394444316},
{"learn":[1278863.092],"iteration":620,"passed_time":1.535339668,"remaining_time":0.9370269471},
{"learn":[1278541.49],"iteration":621,"passed_time":1.537795833,"remaining_time":0.9345447347},
{"learn":[1278093.014],"iteration":622,"passed_time":1.540317297,"remaining_time":0.9321021206},
{"learn":[1277810.559],"iteration":623,"passed_time":1.542570914,"remaining_time":0.9294978584},
{"learn":[1277396.023],"iteration":624,"passed_time":1.547726824,"remaining_time":0.9286360942},
{"learn":[1276872.826],"iteration":625,"passed_time":1.551547107,"remaining_time":0.9269626488},
{"learn":[1276626.201],"iteration":626,"passed_time":1.557300594,"remaining_time":0.9264324105},
{"learn":[1276315.923],"iteration":627,"passed_time":1.561718464,"remaining_time":0.9250943769},
{"learn":[1276093.149],"iteration":628,"passed_time":1.564511075,"remaining_time":0.9227879315},
{"learn":[1275623.951],"iteration":629,"passed_time":1.566650605,"remaining_time":0.9200963873},
{"learn":[1275244.554],"iteration":630,"passed_time":1.568870716,"remaining_time":0.9174537152},
{"learn":[1274309.314],"iteration":631,"passed_time":1.57094722,"remaining_time":0.914728761},
{"learn":[1274029.704],"iteration":632,"passed_time":1.573307065,"remaining_time":0.9121701308},
{"learn":[1273462.803],"iteration":633,"passed_time":1.575946289,"remaining_time":0.90977341},
{"learn":[1272965.309],"iteration":634,"passed_time":1.579267248,"remaining_time":0.9077677885},
{"learn":[1272200.233],"iteration":635,"passed_time":1.582036438,"remaining_time":0.9054422381},
{"learn":[1271904.177],"iteration":636,"passed_time":1.584897591,"remaining_time":0.9031677012},
{"learn":[1271427.72],"iteration":637,"passed_time":1.587091856,"remaining_time":0.900512934},
{"learn":[1271127.099],"iteration":638,"passed_time":1.58999849,"remaining_time":0.8982620578},
{"learn":[1270798.499],"iteration":639,"passed_time":1.592272531,"remaining_time":0.8956532987},
{"learn":[1270362.138],"iteration":640,"passed_time":1.595987533,"remaining_time":0.8938526122},
{"learn":[1269866.173],"iteration":641,"passed_time":1.598605435,"remaining_time":0.8914341833},
{"learn":[1269327.288],"iteration":642,"passed_time":1.600829775,"remaining_time":0.8887966247},
{"learn":[1268905.361],"iteration":643,"passed_time":1.602968467,"remaining_time":0.8861130033},
{"learn":[1268689.555],"iteration":644,"passed_time":1.604967783,"remaining_time":0.8833543615},
{"learn":[1267862.939],"iteration":645,"passed_time":1.607363462,"remaining_time":0.8808152718},
{"learn":[1267596.914],"iteration":646,"passed_time":1.609583243,"remaining_time":0.8781806567},
{"learn":[1267352.176],"iteration":647,"passed_time":1.612168251,"remaining_time":0.8757457164},
{"learn":[1266590.816],"iteration":648,"passed_time":1.615594893,"remaining_time":0.873765497},
{"learn":[1266369.048],"iteration":649,"passed_time":1.617871061,"remaining_time":0.8711613403},
{"learn":[1265934.665],"iteration":650,"passed_time":1.619888732,"remaining_time":0.8684196119},
{"learn":[1265675.667],"iteration":651,"passed_time":1.622211452,"remaining_time":0.8658429222},
{"learn":[1265059.148],"iteration":652,"passed_time":1.624348191,"remaining_time":0.8631681809},
{"learn":[1264714.896],"iteration":653,"passed_time":1.626734612,"remaining_time":0.8606271799},
{"learn":[1264483.729],"iteration":654,"passed_time":1.628918625,"remaining_time":0.857980039},
{"learn":[1264061.19],"iteration":655,"passed_time":1.631408984,"remaining_time":0.8554949552},
{"learn":[1263675.846],"iteration":656,"passed_time":1.633891819,"remaining_time":0.853005927},
{"learn":[1263262.149],"iteration":657,"passed_time":1.636663328,"remaining_time":0.8506669577},
{"learn":[1262651.988],"iteration":658,"passed_time":1.639267975,"remaining_time":0.848240333},
{"learn":[1262115.801],"iteration":659,"passed_time":1.641670371,"remaining_time":0.8457089788},
{"learn":[1261874.043],"iteration":660,"passed_time":1.644716564,"remaining_time":0.8435081926},
{"learn":[1261482.339],"iteration":661,"passed_time":1.646778654,"remaining_time":0.8408023941},
{"learn":[1261131.629],"iteration":662,"passed_time":1.648882871,"remaining_time":0.8381199511},
{"learn":[1260765.777],"iteration":663,"passed_time":1.651822801,"remaining_time":0.83586214},
{"learn":[1260400.572],"iteration":664,"passed_time":1.65457434,"remaining_time":0.8335073745},
{"learn":[1260090.767],"iteration":665,"passed_time":1.656900331,"remaining_time":0.8309380041},
{"learn":[1259864.11],"iteration":666,"passed_time":1.659271603,"remaining_time":0.8283919698},
{"learn":[1259623.327],"iteration":667,"passed_time":1.661358227,"remaining_time":0.8257049871},
{"learn":[1259341.941],"iteration":668,"passed_time":1.663459695,"remaining_time":0.8230271438},
{"learn":[1258639.322],"iteration":669,"passed_time":1.665646702,"remaining_time":0.8203931516},
{"learn":[1258474.757],"iteration":670,"passed_time":1.667644017,"remaining_time":0.817667484},
{"learn":[1258140.782],"iteration":671,"passed_time":1.670326168,"remaining_time":0.8152782485},
{"learn":[1257561.252],"iteration":672,"passed_time":1.673446358,"remaining_time":0.8131009795},
{"learn":[1257268.481],"iteration":673,"passed_time":1.675967075,"remaining_time":0.810630959},
{"learn":[1256614.32],"iteration":674,"passed_time":1.679015973,"remaining_time":0.808415098},
{"learn":[1256242.813],"iteration":675,"passed_time":1.681124351,"remaining_time":0.8057459908},
{"learn":[1255802.159],"iteration":676,"passed_time":1.683157964,"remaining_time":0.8030428693},
{"learn":[1255451.93],"iteration":677,"passed_time":1.685180802,"remaining_time":0.8003366051},
{"learn":[1255204.648],"iteration":678,"passed_time":1.687347419,"remaining_time":0.7977003262},
{"learn":[1254919.082],"iteration":679,"passed_time":1.690220909,"remaining_time":0.7953980749},
{"learn":[1254501.719],"iteration":680,"passed_time":1.692882479,"remaining_time":0.7929948762},
{"learn":[1254160.484],"iteration":681,"passed_time":1.694941579,"remaining_time":0.790310003},
{"learn":[1253561.806],"iteration":682,"passed_time":1.697179462,"remaining_time":0.7877099405},
{"learn":[1253171.507],"iteration":683,"passed_time":1.69948412,"remaining_time":0.7851417865},
{"learn":[1252834.516],"iteration":684,"passed_time":1.701589937,"remaining_time":0.7824829638},
{"learn":[1252408.521],"iteration":685,"passed_time":1.703893949,"remaining_time":0.7799164724},
{"learn":[1251950.172],"iteration":686,"passed_time":1.706125178,"remaining_time":0.7773175845},
{"learn":[1251497.023],"iteration":687,"passed_time":1.710271741,"remaining_time":0.7755883479},
{"learn":[1251114.047],"iteration":688,"passed_time":1.712818312,"remaining_time":0.7731298911},
{"learn":[1250883.867],"iteration":689,"passed_time":1.715151188,"remaining_time":0.7705751713},
{"learn":[1250428.119],"iteration":690,"passed_time":1.717442801,"remaining_time":0.7680026417},
{"learn":[1250227.757],"iteration":691,"passed_time":1.719360026,"remaining_time":0.7652642891},
{"learn":[1249881.352],"iteration":692,"passed_time":1.72179858,"remaining_time":0.7627592554},
{"learn":[1249670.052],"iteration":693,"passed_time":1.724001101,"remaining_time":0.7601503413},
{"learn":[1249164.553],"iteration":694,"passed_time":1.726377588,"remaining_time":0.7576189417},
{"learn":[1248852.9],"iteration":695,"passed_time":1.728879708,"remaining_time":0.755142861},
{"learn":[1248434.541],"iteration":696,"passed_time":1.731498248,"remaining_time":0.7527173158},
{"learn":[1248244.639],"iteration":697,"passed_time":1.734170202,"remaining_time":0.7503143279},
{"learn":[1247955.438],"iteration":698,"passed_time":1.737008965,"remaining_time":0.7479824014},
{"learn":[1247685.234],"iteration":699,"passed_time":1.739391867,"remaining_time":0.7454536574},
{"learn":[1247503.515],"iteration":700,"passed_time":1.742111613,"remaining_time":0.7430690049},
{"learn":[1247068.096],"iteration":701,"passed_time":1.74467488,"remaining_time":0.740616972},
{"learn":[1246769.534],"iteration":702,"passed_time":1.747215743,"remaining_time":0.7381551573},
{"learn":[1246569.127],"iteration":703,"passed_time":1.749837893,"remaining_time":0.7357272958},
{"learn":[1246156.686],"iteration":704,"passed_time":1.751991766,"remaining_time":0.7331029375},
{"learn":[1245902.089],"iteration":705,"passed_time":1.75415921,"remaining_time":0.7304855632},
{"learn":[1245311.696],"iteration":706,"passed_time":1.756492115,"remaining_time":0.7279380333},
{"learn":[1245142.507],"iteration":707,"passed_time":1.758518016,"remaining_time":0.7252644925},
{"learn":[1244804.048],"iteration":708,"passed_time":1.760697031,"remaining_time":0.7226556219},
{"learn":[1244466.173],"iteration":709,"passed_time":1.762518162,"remaining_time":0.7199017846},
{"learn":[1244159.74],"iteration":710,"passed_time":1.764736831,"remaining_time":0.7173121577},
{"learn":[1243849.549],"iteration":711,"passed_time":1.767816621,"remaining_time":0.7150718918},
{"learn":[1243453.408],"iteration":712,"passed_time":1.770569744,"remaining_time":0.7126977793},
{"learn":[1243048.701],"iteration":713,"passed_time":1.773300988,"remaining_time":0.7103138411},
{"learn":[1242758.676],"iteration":714,"passed_time":1.77551804,"remaining_time":0.7077239739},
{"learn":[1242525.842],"iteration":715,"passed_time":1.777515423,"remaining_time":0.7050480171},
{"learn":[1242214.43],"iteration":716,"passed_time":1.779595102,"remaining_time":0.7024064348},
{"learn":[1241758.719],"iteration":717,"passed_time":1.781752708,"remaining_time":0.6997970245},
{"learn":[1241508.823],"iteration":718,"passed_time":1.783727135,"remaining_time":0.6971172809},
{"learn":[1241201.721],"iteration":719,"passed_time":1.786521771,"remaining_time":0.6947584664},
{"learn":[1240636.962],"iteration":720,"passed_time":1.789175039,"remaining_time":0.6923437392},
{"learn":[1240171.487],"iteration":721,"passed_time":1.791206957,"remaining_time":0.6896891052},
{"learn":[1239776.975],"iteration":722,"passed_time":1.793291786,"remaining_time":0.6870564658},
{"learn":[1239576.914],"iteration":723,"passed_time":1.795419809,"remaining_time":0.6844418056},
{"learn":[1239393.056],"iteration":724,"passed_time":1.797591158,"remaining_time":0.6818449219},
{"learn":[1238968.926],"iteration":725,"passed_time":1.799882686,"remaining_time":0.6792945675},
{"learn":[1238571.169],"iteration":726,"passed_time":1.802339517,"remaining_time":0.6768069989},
{"learn":[1238031.443],"iteration":727,"passed_time":1.805697246,"remaining_time":0.6746561138},
{"learn":[1237577.142],"iteration":728,"passed_time":1.809425483,"remaining_time":0.6726396516},
{"learn":[1237041.941],"iteration":729,"passed_time":1.811680528,"remaining_time":0.6700736201},
{"learn":[1236790.623],"iteration":730,"passed_time":1.813825914,"remaining_time":0.6674680858},
{"learn":[1236528.395],"iteration":731,"passed_time":1.815765598,"remaining_time":0.6647884977},
{"learn":[1236215.373],"iteration":732,"passed_time":1.818035329,"remaining_time":0.66223115},
{"learn":[1235979.234],"iteration":733,"passed_time":1.81999635,"remaining_time":0.6595627101},
{"learn":[1235644.175],"iteration":734,"passed_time":1.821967258,"remaining_time":0.6568997596},
{"learn":[1235381.13],"iteration":735,"passed_time":1.824992516,"remaining_time":0.6546168808},
{"learn":[1234898.938],"iteration":736,"passed_time":1.827654457,"remaining_time":0.6522023368},
{"learn":[1234560.521],"iteration":737,"passed_time":1.830863928,"remaining_time":0.6499815028},
{"learn":[1234182.458],"iteration":738,"passed_time":1.833595028,"remaining_time":0.6475890425},
{"learn":[1233988.661],"iteration":739,"passed_time":1.836549481,"remaining_time":0.6452741419},
{"learn":[1233597.728],"iteration":740,"passed_time":1.839095474,"remaining_time":0.6428147475},
{"learn":[1233281.234],"iteration":741,"passed_time":1.842899868,"remaining_time":0.6407926763},
{"learn":[1232983.243],"iteration":742,"passed_time":1.845641614,"remaining_time":0.6383982435},
{"learn":[1232832.943],"iteration":743,"passed_time":1.847840985,"remaining_time":0.635816253},
{"learn":[1232576.69],"iteration":744,"passed_time":1.85002468,"remaining_time":0.633229924},
{"learn":[1232363.984],"iteration":745,"passed_time":1.852097465,"remaining_time":0.6306069116},
{"learn":[1232140.849],"iteration":746,"passed_time":1.854126327,"remaining_time":0.6279704962},
{"learn":[1231712.771],"iteration":747,"passed_time":1.856654299,"remaining_time":0.6255038546},
{"learn":[1231522.957],"iteration":748,"passed_time":1.859291749,"remaining_time":0.6230737369},
{"learn":[1231149.57],"iteration":749,"passed_time":1.862682199,"remaining_time":0.6208940665},
{"learn":[1230674.779],"iteration":750,"passed_time":1.865663516,"remaining_time":0.6185755198},
{"learn":[1230295.775],"iteration":751,"passed_time":1.867944445,"remaining_time":0.6160242319},
{"learn":[1229936.693],"iteration":752,"passed_time":1.870076364,"remaining_time":0.6134247833},
{"learn":[1229800.817],"iteration":753,"passed_time":1.872188481,"remaining_time":0.6108201146},
{"learn":[1229481.444],"iteration":754,"passed_time":1.874370569,"remaining_time":0.6082394563},
{"learn":[1228985.658],"iteration":755,"passed_time":1.878166738,"remaining_time":0.6061807992},
{"learn":[1228854.709],"iteration":756,"passed_time":1.880922235,"remaining_time":0.6037834916},
{"learn":[1228614.895],"iteration":757,"passed_time":1.883130984,"remaining_time":0.6012106835},
{"learn":[1228351.522],"iteration":758,"passed_time":1.885380784,"remaining_time":0.5986518696},
{"learn":[1227850.375],"iteration":759,"passed_time":1.887705257,"remaining_time":0.5961174495},
{"learn":[1227515.469],"iteration":760,"passed_time":1.889925701,"remaining_time":0.5935509099},
{"learn":[1226934.071],"iteration":761,"passed_time":1.892694911,"remaining_time":0.5911566783},
{"learn":[1226449.33],"iteration":762,"passed_time":1.895406894,"remaining_time":0.5887436879},
{"learn":[1225817.58],"iteration":763,"passed_time":1.898949762,"remaining_time":0.5865865758},
{"learn":[1225512.236],"iteration":764,"passed_time":1.902209253,"remaining_time":0.58433879},
{"learn":[1225289.033],"iteration":765,"passed_time":1.904704073,"remaining_time":0.581854769},
{"learn":[1224930.878],"iteration":766,"passed_time":1.907163849,"remaining_time":0.5793600741},
{"learn":[1224613.322],"iteration":767,"passed_time":1.909396763,"remaining_time":0.5767969389},
{"learn":[1224233.172],"iteration":768,"passed_time":1.911837934,"remaining_time":0.5742972207},
{"learn":[1223894.331],"iteration":769,"passed_time":1.914361279,"remaining_time":0.5718222003},
{"learn":[1223505.547],"iteration":770,"passed_time":1.917448172,"remaining_time":0.5695144377},
{"learn":[1223221.424],"iteration":771,"passed_time":1.920087616,"remaining_time":0.5670725083},
{"learn":[1223072.356],"iteration":772,"passed_time":1.92231305,"remaining_time":0.5645084896},
{"learn":[1222864.535],"iteration":773,"passed_time":1.924875429,"remaining_time":0.5620437299},
{"learn":[1222470.386],"iteration":774,"passed_time":1.927470198,"remaining_time":0.5595881221},
{"learn":[1222270.05],"iteration":775,"passed_time":1.929958746,"remaining_time":0.5571014937},
{"learn":[1221965.136],"iteration":776,"passed_time":1.932145251,"remaining_time":0.5545281737},
{"learn":[1221151.298],"iteration":777,"passed_time":1.935123635,"remaining_time":0.5521818085},
{"learn":[1220407.793],"iteration":778,"passed_time":1.938187599,"remaining_time":0.5498580995},
{"learn":[1219883.125],"iteration":779,"passed_time":1.940637949,"remaining_time":0.5473594214},
{"learn":[1219519.064],"iteration":780,"passed_time":1.943040032,"remaining_time":0.5448473329},
{"learn":[1219145.231],"iteration":781,"passed_time":1.945220151,"remaining_time":0.5422736484},
{"learn":[1218649.675],"iteration":782,"passed_time":1.947710992,"remaining_time":0.5397870821},
{"learn":[1218462.182],"iteration":783,"passed_time":1.949716833,"remaining_time":0.5371668827},
{"learn":[1218179.076],"iteration":784,"passed_time":1.95338199,"remaining_time":0.5350027107},
{"learn":[1217698.11],"iteration":785,"passed_time":1.956120371,"remaining_time":0.5325823911},
{"learn":[1217332.392],"iteration":786,"passed_time":1.958854217,"remaining_time":0.5301600359},
{"learn":[1216908.766],"iteration":787,"passed_time":1.9615021,"remaining_time":0.5277137629},
{"learn":[1216573.602],"iteration":788,"passed_time":1.963743576,"remaining_time":0.5251582948},
{"learn":[1216086.209],"iteration":789,"passed_time":1.966260759,"remaining_time":0.5226769106},
{"learn":[1215675.01],"iteration":790,"passed_time":1.968465147,"remaining_time":0.5201127885},
{"learn":[1215243.572],"iteration":791,"passed_time":1.970941234,"remaining_time":0.5176209301},
{"learn":[1214894.727],"iteration":792,"passed_time":1.973797122,"remaining_time":0.5152282526},
{"learn":[1214631.244],"iteration":793,"passed_time":1.976319096,"remaining_time":0.5127477755},
{"learn":[1214314.539],"iteration":794,"passed_time":1.978534182,"remaining_time":0.5101880595},
{"learn":[1213882.449],"iteration":795,"passed_time":1.980948525,"remaining_time":0.5076802752},
{"learn":[1213349.864],"iteration":796,"passed_time":1.983536914,"remaining_time":0.5052170558},
{"learn":[1213036.632],"iteration":797,"passed_time":1.986047667,"remaining_time":0.5027338706},
{"learn":[1212818.092],"iteration":798,"passed_time":1.988498087,"remaining_time":0.5002354386},
{"learn":[1212610.551],"iteration":799,"passed_time":1.991289293,"remaining_time":0.4978223232},
{"learn":[1212454.777],"iteration":800,"passed_time":1.994181958,"remaining_time":0.4954334703},
{"learn":[1212272.678],"iteration":801,"passed_time":1.996721064,"remaining_time":0.4929560731},
{"learn":[1211958.071],"iteration":802,"passed_time":1.999013541,"remaining_time":0.490418017},
{"learn":[1211526.565],"iteration":803,"passed_time":2.001178463,"remaining_time":0.487849476},
{"learn":[1211179.344],"iteration":804,"passed_time":2.003390922,"remaining_time":0.4852934531},
{"learn":[1211027.358],"iteration":805,"passed_time":2.005416759,"remaining_time":0.4826933637},
{"learn":[1210573.781],"iteration":806,"passed_time":2.00762809,"remaining_time":0.4801390599},
{"learn":[1210122.327],"iteration":807,"passed_time":2.010308281,"remaining_time":0.4776970174},
{"learn":[1209771.6],"iteration":808,"passed_time":2.01341608,"remaining_time":0.4753553414},
{"learn":[1209468.861],"iteration":809,"passed_time":2.015757291,"remaining_time":0.4728319571},
{"learn":[1209312.587],"iteration":810,"passed_time":2.018322916,"remaining_time":0.4703613207},
{"learn":[1208891.772],"iteration":811,"passed_time":2.021021133,"remaining_time":0.4679211489},
{"learn":[1208643.2],"iteration":812,"passed_time":2.02365394,"remaining_time":0.4654652973},
{"learn":[1208346.885],"iteration":813,"passed_time":2.02578714,"remaining_time":0.4628948501},
{"learn":[1208180.824],"iteration":814,"passed_time":2.027889536,"remaining_time":0.4603184837},
{"learn":[1207915.392],"iteration":815,"passed_time":2.031049137,"remaining_time":0.4579816683},
{"learn":[1207609.563],"iteration":816,"passed_time":2.0335207,"remaining_time":0.4554887246},
{"learn":[1206962.379],"iteration":817,"passed_time":2.035789874,"remaining_time":0.4529508033},
{"learn":[1206744.936],"iteration":818,"passed_time":2.0381028,"remaining_time":0.4504232072},
{"learn":[1206563.978],"iteration":819,"passed_time":2.040265441,"remaining_time":0.4478631455},
{"learn":[1206228.249],"iteration":820,"passed_time":2.042532231,"remaining_time":0.4453267593},
{"learn":[1205941.276],"iteration":821,"passed_time":2.044786278,"remaining_time":0.4427882695},
{"learn":[1205727.695],"iteration":822,"passed_time":2.046941364,"remaining_time":0.4402291876},
{"learn":[1205532.322],"iteration":823,"passed_time":2.049721375,"remaining_time":0.4378045654},
{"learn":[1205342.186],"iteration":824,"passed_time":2.052956874,"remaining_time":0.4354757005},
{"learn":[1205267.352],"iteration":825,"passed_time":2.055209332,"remaining_time":0.432937559},
{"learn":[1204691.774],"iteration":826,"passed_time":2.059097581,"remaining_time":0.4307422993},
{"learn":[1204348.414],"iteration":827,"passed_time":2.063508134,"remaining_time":0.4286514482},
{"learn":[1204066.73],"iteration":828,"passed_time":2.065788964,"remaining_time":0.4261156971},
{"learn":[1203844.511],"iteration":829,"passed_time":2.070423178,"remaining_time":0.4240625787},
{"learn":[1203431.07],"iteration":830,"passed_time":2.073524949,"remaining_time":0.4216915961},
{"learn":[1203107.666],"iteration":831,"passed_time":2.075794205,"remaining_time":0.419150753},
{"learn":[1202738.025],"iteration":832,"passed_time":2.078283978,"remaining_time":0.4166547711},
{"learn":[1202233.146],"iteration":833,"passed_time":2.080683767,"remaining_time":0.4141408937},
{"learn":[1202073.573],"iteration":834,"passed_time":2.083129307,"remaining_time":0.4116363302},
{"learn":[1201625.384],"iteration":835,"passed_time":2.085286282,"remaining_time":0.4090752994},
{"learn":[1201259.545],"iteration":836,"passed_time":2.090149969,"remaining_time":0.4070423477},
{"learn":[1201053.906],"iteration":837,"passed_time":2.092532699,"remaining_time":0.4045230277},
{"learn":[1200717.061],"iteration":838,"passed_time":2.094875946,"remaining_time":0.4019964569},
{"learn":[1200299.72],"iteration":839,"passed_time":2.097491939,"remaining_time":0.3995222741},
{"learn":[1199907.184],"iteration":840,"passed_time":2.09958961,"remaining_time":0.3969497598},
{"learn":[1199721.831],"iteration":841,"passed_time":2.101631723,"remaining_time":0.394367948},
{"learn":[1199187.491],"iteration":842,"passed_time":2.103869555,"remaining_time":0.3918238673},
{"learn":[1199048.351],"iteration":843,"passed_time":2.106118017,"remaining_time":0.389282477},
{"learn":[1198882.028],"iteration":844,"passed_time":2.108758118,"remaining_time":0.3868136193},
{"learn":[1198500.517],"iteration":845,"passed_time":2.111963953,"remaining_time":0.384447339},
{"learn":[1198346.892],"iteration":846,"passed_time":2.113970268,"remaining_time":0.3818623979},
{"learn":[1198074.889],"iteration":847,"passed_time":2.116589322,"remaining_time":0.379388652},
{"learn":[1197891.133],"iteration":848,"passed_time":2.118659325,"remaining_time":0.3768169118},
{"learn":[1197745.787],"iteration":849,"passed_time":2.121012802,"remaining_time":0.3742963768},
{"learn":[1197578.179],"iteration":850,"passed_time":2.123560829,"remaining_time":0.3718102979},
{"learn":[1197380.167],"iteration":851,"passed_time":2.125952007,"remaining_time":0.3692968275},
{"learn":[1197191.458],"iteration":852,"passed_time":2.128483145,"remaining_time":0.3668077635},
{"learn":[1196870.537],"iteration":853,"passed_time":2.130887889,"remaining_time":0.3642969928},
{"learn":[1196708.934],"iteration":854,"passed_time":2.132854098,"remaining_time":0.3617120985},
{"learn":[1196553.417],"iteration":855,"passed_time":2.134991972,"remaining_time":0.359157528},
{"learn":[1196418.653],"iteration":856,"passed_time":2.137179127,"remaining_time":0.3566121531},
{"learn":[1196100.641],"iteration":857,"passed_time":2.13926639,"remaining_time":0.3540510809},
{"learn":[1195930.525],"iteration":858,"passed_time":2.141415189,"remaining_time":0.3515012126},
{"learn":[1195729.972],"iteration":859,"passed_time":2.143636632,"remaining_time":0.3489641029},
{"learn":[1195359.451],"iteration":860,"passed_time":2.14714284,"remaining_time":0.3466351391},
{"learn":[1195195.625],"iteration":861,"passed_time":2.149909114,"remaining_time":0.3441849857},
{"learn":[1195011.083],"iteration":862,"passed_time":2.152700288,"remaining_time":0.3417380527},
{"learn":[1194767.585],"iteration":863,"passed_time":2.154868288,"remaining_time":0.3391922305},
{"learn":[1194663.176],"iteration":864,"passed_time":2.156831306,"remaining_time":0.3366152905},
{"learn":[1194189.302],"iteration":865,"passed_time":2.15907255,"remaining_time":0.3340828194},
{"learn":[1193949.54],"iteration":866,"passed_time":2.161138555,"remaining_time":0.3315241381},
{"learn":[1193849.198],"iteration":867,"passed_time":2.164590576,"remaining_time":0.3291773686},
{"learn":[1193699.857],"iteration":868,"passed_time":2.167116041,"remaining_time":0.326688379},
{"learn":[1193336.889],"iteration":869,"passed_time":2.169699858,"remaining_time":0.3242080248},
{"learn":[1193036.325],"iteration":870,"passed_time":2.171961299,"remaining_time":0.3216796872},
{"learn":[1192904.43],"iteration":871,"passed_time":2.174254631,"remaining_time":0.3191566431},
{"learn":[1192494.602],"iteration":872,"passed_time":2.176534229,"remaining_time":0.3166321273},
{"learn":[1192223.073],"iteration":873,"passed_time":2.178740771,"remaining_time":0.3140976397},
{"learn":[1192056.755],"iteration":874,"passed_time":2.181095792,"remaining_time":0.3115851131},
{"learn":[1191895.386],"iteration":875,"passed_time":2.184196946,"remaining_time":0.3091785632},
{"learn":[1191665.599],"iteration":876,"passed_time":2.186931336,"remaining_time":0.3067189901},
{"learn":[1191407.835],"iteration":877,"passed_time":2.189154901,"remaining_time":0.3041878108},
{"learn":[1191154.36],"iteration":878,"passed_time":2.191224324,"remaining_time":0.3016361129},
{"learn":[1191012.527],"iteration":879,"passed_time":2.193299147,"remaining_time":0.2990862473},
{"learn":[1190552.193],"iteration":880,"passed_time":2.195401382,"remaining_time":0.2965411629},
{"learn":[1190242.717],"iteration":881,"passed_time":2.197495568,"remaining_time":0.2939960057},
{"learn":[1190009.465],"iteration":882,"passed_time":2.199855654,"remaining_time":0.2914871025},
{"learn":[1189737.012],"iteration":883,"passed_time":2.202268032,"remaining_time":0.2889853978},
{"learn":[1189505.504],"iteration":884,"passed_time":2.205302001,"remaining_time":0.2865646667},
{"learn":[1189382.126],"iteration":885,"passed_time":2.207750902,"remaining_time":0.2840672718},
{"learn":[1188988.204],"iteration":886,"passed_time":2.209944192,"remaining_time":0.2815374225},
{"learn":[1188674.834],"iteration":887,"passed_time":2.212306657,"remaining_time":0.2790296684},
{"learn":[1188478.733],"iteration":888,"passed_time":2.215493425,"remaining_time":0.2766251633},
{"learn":[1188327.51],"iteration":889,"passed_time":2.217768479,"remaining_time":0.2741062165},
{"learn":[1188165.296],"iteration":890,"passed_time":2.219842289,"remaining_time":0.2715631981},
{"learn":[1187915.869],"iteration":891,"passed_time":2.222508393,"remaining_time":0.2690929444},
{"learn":[1187557.468],"iteration":892,"passed_time":2.225718958,"remaining_time":0.2666874899},
{"learn":[1187424.726],"iteration":893,"passed_time":2.227791118,"remaining_time":0.2641452556},
{"learn":[1187026.66],"iteration":894,"passed_time":2.230115873,"remaining_time":0.2616337058},
{"learn":[1186841.7],"iteration":895,"passed_time":2.232281537,"remaining_time":0.259104107},
{"learn":[1186482.384],"iteration":896,"passed_time":2.23442443,"remaining_time":0.2565727048},
{"learn":[1186322.739],"iteration":897,"passed_time":2.236395921,"remaining_time":0.2540226993},
{"learn":[1186213.69],"iteration":898,"passed_time":2.238373188,"remaining_time":0.2514746295},
{"learn":[1185842.572],"iteration":899,"passed_time":2.241316912,"remaining_time":0.2490352125},
{"learn":[1185593.807],"iteration":900,"passed_time":2.244255938,"remaining_time":0.2465941596},
{"learn":[1185190.499],"iteration":901,"passed_time":2.247379351,"remaining_time":0.2441720359},
{"learn":[1185053.766],"iteration":902,"passed_time":2.250696955,"remaining_time":0.2417692188},
{"learn":[1184676.85],"iteration":903,"passed_time":2.253682511,"remaining_time":0.2393291163},
{"learn":[1184501.021],"iteration":904,"passed_time":2.256508183,"remaining_time":0.2368710247},
{"learn":[1184317.005],"iteration":905,"passed_time":2.258446023,"remaining_time":0.2343200068},
{"learn":[1183939.372],"iteration":906,"passed_time":2.260926775,"remaining_time":0.2318260089},
{"learn":[1183832.725],"iteration":907,"passed_time":2.263418963,"remaining_time":0.2293331989},
{"learn":[1183596.821],"iteration":908,"passed_time":2.265822581,"remaining_time":0.2268315235},
{"learn":[1183472.529],"iteration":909,"passed_time":2.267899075,"remaining_time":0.2242977107},
{"learn":[1183201.992],"iteration":910,"passed_time":2.270244098,"remaining_time":0.2217911358},
{"learn":[1183056.542],"iteration":911,"passed_time":2.272355272,"remaining_time":0.2192623508},
{"learn":[1182819.18],"iteration":912,"passed_time":2.274849328,"remaining_time":0.2167709655},
{"learn":[1182593.266],"iteration":913,"passed_time":2.27712036,"remaining_time":0.2142585897},
{"learn":[1182384.79],"iteration":914,"passed_time":2.280282239,"remaining_time":0.2118294976},
{"learn":[1182097.22],"iteration":915,"passed_time":2.283074238,"remaining_time":0.2093648864},
{"learn":[1181801.611],"iteration":916,"passed_time":2.285869077,"remaining_time":0.2068998183},
{"learn":[1181635.493],"iteration":917,"passed_time":2.288116162,"remaining_time":0.2043851038},
{"learn":[1181435.881],"iteration":918,"passed_time":2.290097144,"remaining_time":0.2018475176},
{"learn":[1181241.57],"iteration":919,"passed_time":2.292100784,"remaining_time":0.1993131117},
{"learn":[1181091.495],"iteration":920,"passed_time":2.294164407,"remaining_time":0.1967850034},
{"learn":[1180816.018],"iteration":921,"passed_time":2.296218981,"remaining_time":0.1942571372},
{"learn":[1180577.728],"iteration":922,"passed_time":2.298579312,"remaining_time":0.1917558039},
{"learn":[1180456.023],"iteration":923,"passed_time":2.301065015,"remaining_time":0.1892650878},
{"learn":[1180306.731],"iteration":924,"passed_time":2.303535532,"remaining_time":0.1867731512},
{"learn":[1180180.482],"iteration":925,"passed_time":2.305671695,"remaining_time":0.1842545415},
{"learn":[1179863.037],"iteration":926,"passed_time":2.308294425,"remaining_time":0.1817750734},
{"learn":[1179704.322],"iteration":927,"passed_time":2.310513006,"remaining_time":0.1792639401},
{"learn":[1179408.838],"iteration":928,"passed_time":2.312931076,"remaining_time":0.1767686829},
{"learn":[1179212.509],"iteration":929,"passed_time":2.316123305,"remaining_time":0.1743318617},
{"learn":[1179069.133],"iteration":930,"passed_time":2.319045497,"remaining_time":0.1718734042},
{"learn":[1178890.078],"iteration":931,"passed_time":2.32162136,"remaining_time":0.1693886829},
{"learn":[1178819.132],"iteration":932,"passed_time":2.323703859,"remaining_time":0.1668683372},
{"learn":[1178658.808],"iteration":933,"passed_time":2.325646262,"remaining_time":0.1643390292},
{"learn":[1178434.479],"iteration":934,"passed_time":2.328264966,"remaining_time":0.1618579923},
{"learn":[1178230.904],"iteration":935,"passed_time":2.330408999,"remaining_time":0.159344205},
{"learn":[1178169.172],"iteration":936,"passed_time":2.33247116,"remaining_time":0.1568257023},
{"learn":[1178008.031],"iteration":937,"passed_time":2.33464779,"remaining_time":0.1543157388},
{"learn":[1177864.325],"iteration":938,"passed_time":2.337041784,"remaining_time":0.1518206058},
{"learn":[1177739.636],"iteration":939,"passed_time":2.339681614,"remaining_time":0.1493413796},
{"learn":[1177603.244],"iteration":940,"passed_time":2.342440407,"remaining_time":0.146869271},
{"learn":[1177495.085],"iteration":941,"passed_time":2.345323479,"remaining_time":0.1444042057},
{"learn":[1177252.79],"iteration":942,"passed_time":2.347639754,"remaining_time":0.1419039936},
{"learn":[1176980.422],"iteration":943,"passed_time":2.350041492,"remaining_time":0.139409241},
{"learn":[1176597.554],"iteration":944,"passed_time":2.354199642,"remaining_time":0.1370169104},
{"learn":[1176108.414],"iteration":945,"passed_time":2.356854885,"remaining_time":0.1345350568},
{"learn":[1175831.347],"iteration":946,"passed_time":2.359286451,"remaining_time":0.1320403188},
{"learn":[1175608.54],"iteration":947,"passed_time":2.362620386,"remaining_time":0.1295952111},
{"learn":[1175434.731],"iteration":948,"passed_time":2.364941752,"remaining_time":0.1270938138},
{"learn":[1175305.979],"iteration":949,"passed_time":2.366989043,"remaining_time":0.1245783707},
{"learn":[1175116.886],"iteration":950,"passed_time":2.369345852,"remaining_time":0.1220798599},
{"learn":[1174924.13],"iteration":951,"passed_time":2.371564489,"remaining_time":0.1195746801},
{"learn":[1174627.327],"iteration":952,"passed_time":2.374093488,"remaining_time":0.1170854081},
{"learn":[1174232.046],"iteration":953,"passed_time":2.37821962,"remaining_time":0.1146730634},
{"learn":[1174175.483],"iteration":954,"passed_time":2.381115865,"remaining_time":0.1121991769},
{"learn":[1173863.619],"iteration":955,"passed_time":2.383299433,"remaining_time":0.1096916057},
{"learn":[1173417.215],"iteration":956,"passed_time":2.38602908,"remaining_time":0.1072092481},
{"learn":[1173300.33],"iteration":957,"passed_time":2.388002246,"remaining_time":0.1046932091},
{"learn":[1173156.898],"iteration":958,"passed_time":2.390154685,"remaining_time":0.1021859667},
{"learn":[1173101.413],"iteration":959,"passed_time":2.392252301,"remaining_time":0.09967717919},
{"learn":[1172916.903],"iteration":960,"passed_time":2.394619929,"remaining_time":0.09718020524},
{"learn":[1172583.431],"iteration":961,"passed_time":2.397522178,"remaining_time":0.09470461824},
{"learn":[1172167.26],"iteration":962,"passed_time":2.400926994,"remaining_time":0.0922474546},
{"learn":[1171989.474],"iteration":963,"passed_time":2.403650018,"remaining_time":0.08976286376},
{"learn":[1171825.386],"iteration":964,"passed_time":2.406097495,"remaining_time":0.0872677848},
{"learn":[1171596.488],"iteration":965,"passed_time":2.409243034,"remaining_time":0.08479737386},
{"learn":[1171393.686],"iteration":966,"passed_time":2.411337491,"remaining_time":0.08228969721},
{"learn":[1171233.69],"iteration":967,"passed_time":2.413746502,"remaining_time":0.07979327281},
{"learn":[1171063.713],"iteration":968,"passed_time":2.416796172,"remaining_time":0.0773175246},
{"learn":[1170869.009],"iteration":969,"passed_time":2.419791434,"remaining_time":0.07483891033},
{"learn":[1170654.41],"iteration":970,"passed_time":2.422137092,"remaining_time":0.07233983075},
{"learn":[1170502.546],"iteration":971,"passed_time":2.424346894,"remaining_time":0.06983715333},
{"learn":[1170352.631],"iteration":972,"passed_time":2.426562767,"remaining_time":0.06733524637},
{"learn":[1170231.153],"iteration":973,"passed_time":2.428685184,"remaining_time":0.06483143201},
{"learn":[1170018.149],"iteration":974,"passed_time":2.430988434,"remaining_time":0.06233303677},
{"learn":[1169829.25],"iteration":975,"passed_time":2.434060312,"remaining_time":0.05985394209},
{"learn":[1169451.816],"iteration":976,"passed_time":2.437415371,"remaining_time":0.05738030044},
{"learn":[1169377.7],"iteration":977,"passed_time":2.440014123,"remaining_time":0.05488784327},
{"learn":[1169134.63],"iteration":978,"passed_time":2.442829344,"remaining_time":0.05239981227},
{"learn":[1168895.823],"iteration":979,"passed_time":2.444739918,"remaining_time":0.04989265138},
{"learn":[1168706.724],"iteration":980,"passed_time":2.447226112,"remaining_time":0.04739785539},
{"learn":[1168457.884],"iteration":981,"passed_time":2.449604788,"remaining_time":0.04490110608},
{"learn":[1168186.473],"iteration":982,"passed_time":2.451951007,"remaining_time":0.04240403573},
{"learn":[1168069.071],"iteration":983,"passed_time":2.45450575,"remaining_time":0.0399106626},
{"learn":[1167964.328],"iteration":984,"passed_time":2.457595006,"remaining_time":0.03742530466},
{"learn":[1167874.607],"iteration":985,"passed_time":2.459741087,"remaining_time":0.03492532983},
{"learn":[1167668.242],"iteration":986,"passed_time":2.462049622,"remaining_time":0.03242821184},
{"learn":[1167532.407],"iteration":987,"passed_time":2.464340213,"remaining_time":0.02993125765},
{"learn":[1167342.84],"iteration":988,"passed_time":2.466992998,"remaining_time":0.02743874922},
{"learn":[1167131.705],"iteration":989,"passed_time":2.469649894,"remaining_time":0.02494595853},
{"learn":[1166861.663],"iteration":990,"passed_time":2.47198433,"remaining_time":0.02244990814},
{"learn":[1166657.516],"iteration":991,"passed_time":2.475816576,"remaining_time":0.01996626271},
{"learn":[1166557.254],"iteration":992,"passed_time":2.478448239,"remaining_time":0.01747143774},
{"learn":[1166213.434],"iteration":993,"passed_time":2.481067902,"remaining_time":0.014976265},
{"learn":[1166122.883],"iteration":994,"passed_time":2.483061076,"remaining_time":0.01247769385},
{"learn":[1165952.205],"iteration":995,"passed_time":2.485323194,"remaining_time":0.009981217646},
{"learn":[1165631.828],"iteration":996,"passed_time":2.487746007,"remaining_time":0.007485695107},
{"learn":[1165537.182],"iteration":997,"passed_time":2.489909732,"remaining_time":0.004989799062},
{"learn":[1165363.212],"iteration":998,"passed_time":2.492501629,"remaining_time":0.002494996625},
{"learn":[1165133.528],"iteration":999,"passed_time":2.495703951,"remaining_time":0}
]}